Workbook

Sheet CHART
A1: THE MASTER'S PLACE INT'L CHURCH
A2: OUR PERFORMANCE (2025)
A4: Revenue:
A5: 2.3531792e+09 | C5: 2.3531792e+09
A7: Recurrent Expenditure (Less Kingdom Investment)
A8: ='Financial Activites'!B81-'Financial Activites'!B80 -> 1303296287
A10: Building (Dremland Phase 1)
A11: =Cashflow!B14*-1 -> 810631000
A13: Other Capital Expenditure
A14: =(Cashflow!B15+Cashflow!B16+Cashflow!B17+Cashflow!B18)*-1 -> 12301200
A15: Kingdom Investment
A16: ='Income - 12 Period'!N75 -> 219705000
A18: Surplus:
A19: =Cashflow!B29 -> 7245705.7
A40: Recurrent Expenditure | B40: =A8 -> 1303296287
A41: Building | B41: =A11 -> 810631000
A42: Other Capital Expenditure | B42: =A14 -> 12301200
A43: Surplus | B43: =A19 -> 7245705.7
A44: Kingdom Investment | B44: =A16 -> 219705000

Sheet Income Analysis
A1: THE MASTER'S PLACE INT'L CHURCH
A2: TWELVE MONTHS INCOME ANALYSIS
A3: For the Year Ended 31ST December 2025
A5: Description | B5: AMOUNT
A6: Balance Brought Forward | B6: ='Financial Activites'!B6 -> 32971800
A7: Income Heads
A8: Home Connect Offering | B8: =VLOOKUP(A8,'Financial Activites'!A9:B84,2,0) -> 2775940
A9: OFFERING | B9: =VLOOKUP(A9,'Financial Activites'!A10:B85,2,0) -> 218363208
A10: PROJECT OFFERING | B10: =VLOOKUP(A10,'Financial Activites'!A11:B86,2,0) -> 1098059628
A11: SACRIFICE | B11: =VLOOKUP(A11,'Financial Activites'!A12:B87,2,0) -> 678458989
A12: SALE OF MATERIAL OFFERING | B12: =VLOOKUP(A12,'Financial Activites'!A13:B88,2,0) -> 0
A13: STUDIO-RESOURCE MATERIAL | B13: =VLOOKUP(A13,'Financial Activites'!A14:B89,2,0) -> 16599182
A14: THANKSGIVING OFFERING | B14: =VLOOKUP(A14,'Financial Activites'!A15:B90,2,0) -> 53876032
A15: TITHE | B15: =VLOOKUP(A15,'Financial Activites'!A16:B91,2,0) -> 218955218
A16: TMA FEE | B16: =VLOOKUP(A16,'Financial Activites'!A17:B92,2,0) -> 2000
A17: Interest Received from FX | B17: =VLOOKUP(A17,'Financial Activites'!A18:B93,2,0) -> 0
A18: Total | B18: =SUM(B6:B17) -> 2.320062e+09
A20: 20% Remittance from TMP Campuses
A21: TMP BENIN | B21: =VLOOKUP(A21,'Financial Activites'!A18:B39,2,0) -> 3421013
A22: TMP OGBOMOSO | B22: =VLOOKUP(A22,'Financial Activites'!A19:B40,2,0) -> 6696000
A23: TMP SAPELE | B23: =VLOOKUP(A23,'Financial Activites'!A20:B41,2,0) -> 1925451
A24: TMP PORTHARCOURT | B24: =VLOOKUP(A24,'Financial Activites'!A21:B42,2,0) -> 1275736
A25: TMP UGHELI | B25: =VLOOKUP(A25,'Financial Activites'!A22:B43,2,0) -> 10666274
A26: TMP LAGOS | B26: =VLOOKUP(A26,'Financial Activites'!A23:B44,2,0) -> 1357000
A27: Total | B27: =SUM(B21:B26) -> 25341474
A29: Income from Satellite Churches
A30: TMP Ebrumede | B30: =VLOOKUP(A30,'Financial Activites'!A27:B46,2,0) -> 336600
A31: TMP Orhuwhorun | B31: =VLOOKUP(A31,'Financial Activites'!A28:B47,2,0) -> 800192
A32: TMP Osubi | B32: =VLOOKUP(A32,'Financial Activites'!A29:B48,2,0) -> 1130000
A33: TMP Otokutu | B33: =VLOOKUP(A33,'Financial Activites'!A30:B49,2,0) -> 726285
A34: TMP Ubeji | B34: =VLOOKUP(A34,'Financial Activites'!A31:B50,2,0) -> 94047
A35: TMP Udu | B35: =VLOOKUP(A35,'Financial Activites'!A32:B51,2,0) -> 794300
A36: TMP Ugbuwangue | B36: =VLOOKUP(A36,'Financial Activites'!A33:B52,2,0) -> 464878
A37: TMP Ughoton | B37: =VLOOKUP(A37,'Financial Activites'!A34:B53,2,0) -> 694720
A38: TMP Warri Central | B38: =VLOOKUP(A38,'Financial Activites'!A35:B54,2,0) -> 2625000
A39: TMP Warri G.R.A | B39: =VLOOKUP(A39,'Financial Activites'!A36:B55,2,0) -> 109700
A40: Total | B40: =SUM(B30:B39) -> 7775722
A42: TOTAL REVENUE | B42: =B40+B27+B18 -> 2.3531792e+09

Sheet Financial Activites
A1: THE MASTER'S PLACE INT'L CHURCH
A2: TWELVE MONTHS INCOME ANALYSIS
A3: For the Year Ended 31ST December 2025
B5: AMOUNT
A6: Opening Balance | B6: ='Income - 12 Period'!N2 -> 32971800
A7: Revenues (A)
A8: Column1 | B8: Column2
A9: Home Connect Offering | B9: =VLOOKUP(Table1[[#This Row],[Column1]],'Income - 12 Period'!A4:N101,14,0) -> 2775940
A10: OFFERING | B10: =VLOOKUP(Table1[[#This Row],[Column1]],'Income - 12 Period'!A5:N102,14,0) -> 218363208
A11: PROJECT OFFERING | B11: =VLOOKUP(Table1[[#This Row],[Column1]],'Income - 12 Period'!A6:N103,14,0) -> 1098059628
A12: SACRIFICE | B12: =VLOOKUP(Table1[[#This Row],[Column1]],'Income - 12 Period'!A7:N104,14,0) -> 678458989
A13: SALE OF MATERIAL OFFERING | B13: =VLOOKUP(Table1[[#This Row],[Column1]],'Income - 12 Period'!A8:N105,14,0) -> 0
A14: STUDIO-RESOURCE MATERIAL | B14: =VLOOKUP(Table1[[#This Row],[Column1]],'Income - 12 Period'!A9:N106,14,0) -> 16599182
A15: THANKSGIVING OFFERING | B15: =VLOOKUP(Table1[[#This Row],[Column1]],'Income - 12 Period'!A10:N107,14,0) -> 53876032
A16: TITHE | B16: =VLOOKUP(A16,'Income - 12 Period'!A3:N101,14,0) -> 218955218
A17: TMA FEE | B17: ='Income - 12 Period'!N12 -> 2000
A18: TMP BENIN | B18: =VLOOKUP(A18,'Income - 12 Period'!A5:N103,14,0) -> 3421013
A19: TMP OGBOMOSO | B19: =VLOOKUP(A19,'Income - 12 Period'!A6:N104,14,0) -> 6696000
A20: TMP SAPELE | B20: =VLOOKUP(A20,'Income - 12 Period'!A7:N105,14,0) -> 1925451
A21: TMP PORTHARCOURT | B21: =VLOOKUP(A21,'Income - 12 Period'!A8:N106,14,0) -> 1275736
A22: TMP UGHELI | B22: =VLOOKUP(A22,'Income - 12 Period'!A8:N106,14,0) -> 10666274
A23: TMP LAGOS | B23: =VLOOKUP(A23,'Income - 12 Period'!A9:N107,14,0) -> 1357000
A24: Total Revenues | B24: =SUM(B6:B23) -> 2.3454035e+09
A26: Other Income (B)
A27: Interest Received from FX | B27: =VLOOKUP(A27,'Income - 12 Period'!A12:N110,14,0) -> 0
A28: TMP Ebrumede | B28: =VLOOKUP(A28,'Income - 12 Period'!A13:N111,14,0) -> 336600
A29: TMP Orhuwhorun | B29: =VLOOKUP(A29,'Income - 12 Period'!A14:N112,14,0) -> 800192
A30: TMP Osubi | B30: =VLOOKUP(A30,'Income - 12 Period'!A15:N113,14,0) -> 1130000
A31: TMP Otokutu | B31: =VLOOKUP(A31,'Income - 12 Period'!A17:N114,14,0) -> 726285
A32: TMP Ubeji | B32: =VLOOKUP(A32,'Income - 12 Period'!A19:N115,14,0) -> 94047
A33: TMP Udu | B33: =VLOOKUP(A33,'Income - 12 Period'!A20:N116,14,0) -> 794300
A34: TMP Ugbuwangue | B34: =VLOOKUP(A34,'Income - 12 Period'!A21:N117,14,0) -> 464878
A35: TMP Ughoton | B35: =VLOOKUP(A35,'Income - 12 Period'!A22:N118,14,0) -> 694720
A36: TMP Warri Central | B36: =VLOOKUP(A36,'Income - 12 Period'!A23:N119,14,0) -> 2625000
A37: TMP Warri G.R.A | B37: =VLOOKUP(A37,'Income - 12 Period'!A24:N120,14,0) -> 109700
A38: Total for other Income | B38: =SUM(B27:B37) -> 7775722
A40: TOTAL REVENUE | B40: =B24+B38 -> 2.3531792e+09 | C40: =B40-'Income Analysis'!B42 -> 0
A42: Expenditure (C)
A43: Advert & Publicity | B43: =VLOOKUP(A43,'Income - 12 Period'!A30:N126,14,0) -> 100081404
A44: Allowances and Bonus | B44: =VLOOKUP(A44,'Income - 12 Period'!A31:N127,14,0) -> 6990000
A45: Bank Charges | B45: =VLOOKUP(A45,'Income - 12 Period'!A32:N128,14,0) -> 5455986
A46: Chairs/Canopies Rent | B46: =VLOOKUP(A46,'Income - 12 Period'!A33:N129,14,0) -> 27813000
A47: Church Service Expense | B47: =VLOOKUP(A47,'Income - 12 Period'!A34:N130,14,0) -> 5192000
A48: Consumables | B48: =VLOOKUP(A48,'Income - 12 Period'!A35:N131,14,0) -> 5168370
A49: Diesel | B49: =VLOOKUP(A49,'Income - 12 Period'!A36:N132,14,0) -> 92848500
A50: Electricity | B50: =VLOOKUP(A50,'Income - 12 Period'!A37:N133,14,0) -> 1338000
A51: Entertainment | B51: =VLOOKUP(A51,'Income - 12 Period'!A38:N134,14,0) -> 14922800
A52: Forex Expense | B52: =VLOOKUP(A52,'Income - 12 Period'!A39:N135,14,0) -> 3788000
A53: Fuel | B53: =VLOOKUP(A53,'Income - 12 Period'!A40:N136,14,0) -> 30348000
A54: Generator Repairs & Mtce | B54: =VLOOKUP(A54,'Income - 12 Period'!A41:N137,14,0) -> 3479200
... A80: Kingdom Investment | B80: =VLOOKUP(A80,'Income - 12 Period'!A67:N163,14,0) -> 219705000
A81: Total Expenses | B81: =SUM(B43:B80) -> 1523001287
A83: Net Income | B83: =-(ROUND(-B40+B81, 5)) -> 8.3017791e+08
B84: =B81-B80 -> 1303296287

Sheet Cashflow
A1: THE MASTER'S PLACE INT'L CHURCH
A2: TWELVE MONTHS INCOME ANALYSIS
A3: For the Year Ended 31ST December 2025
B5: 2025
A6: Cash Flows from Operating Activities
A7: Net Income | B7: ='Financial Activites'!B83 -> 8.3017791e+08
B8: =ROUND(SUBTOTAL(9, B5:B7), 5) -> 8.3017791e+08
A10: Net Cash provided by Operations | B10: =-(ROUND(-B8, 5)) -> 8.3017791e+08
A13: Cash Flow from Investing Activities
A14: Building | B14: ='Income - 12 Period'!N82 -> -810631000
A15: Equipment | B15: ='Income - 12 Period'!N83 -> -6196600
A16: Furniture and Fittings | B16: ='Income - 12 Period'!N84 -> -6104600
A17: Motor Vehicles | B17: ='Income - 12 Period'!N86 -> 0
A18: Land | B18: ='Income - 12 Period'!N85 -> 0
A20: Net cash used in investing | B20: =ROUND(SUBTOTAL(9, B12:B19), 5) -> -822932200
A23: Cash Flows from Financing Activities
A24: Premium Bank | B24: 0
A25: Zenith Resourse | B25: ='Income - 12 Period'!I94 -> 0
A27: Net cash used in financing | B27: =ROUND(SUBTOTAL(9, B24:B25), 5) -> 0
A29: Net increase in cash | B29: =-(ROUND(-B10+-B20+-B27, 5)) -> 7245705.7
A34: Summary
A35: Cash Balance at End of Period | B35: =B29 -> 7245705.7
A36: Cash Balance at Beg of Period | B36: =#REF! -> #REF!
A38: Net Increase <Decrease> in Cash | B38: =ROUND(SUBTOTAL(9, B31:B37), 5) -> #REF!

Sheet Income - 12 Period
A1: DESCRIPTION | B1: JANUARY | C1: FEBRUARY | D1: MARCH | E1: APRIL | F1: MAY | G1: JUNE | H1: JULY | I1: AUGUST | J1: SEPTEMBER | K1: OCTOBER | L1: NOVEMBER | M1: DECEMBER | N1: TOTAL
A2: TWELVE MONTHS INCOME ANALYSIS | B2: 32971800 | C2: 4820388.5 | D2: 5921124.5 | E2: 4774147.8 | F2: 5297933 | G2: 2928743.4 | H2: 4757226.9 | I2: 9349171 | J2: 6902476 | K2: 3640852.4 | L2: 3939670 | M2: 5498237.1 | N2: =B2 -> 32971800
A3: Revenues (A)
A4: Home Connect Offering | B4: 222750 | C4: 71000 | D4: 68400 | E4: 354410 | F4: 340170 | G4: 0 | H4: 343310 | I4: 0 | J4: 293770 | K4: 379130 | L4: 371430 | M4: 331570 | N4: =M4+L4+K4+J4+I4+H4+G4+F4+E4+D4+C4+B4 -> 2775940
A5: OFFERING | B5: 22085703 | C5: 13593838 | D5: 16251845 | E5: 15344866 | F5: 14883258 | G5: 18114551 | H5: 31564548 | I5: 19925622 | J5: 17200306 | K5: 16114207 | L5: 16806275 | M5: 16478189 | N5: =M5+L5+K5+J5+I5+H5+G5+F5+E5+D5+C5+B5 -> 218363208
A6: PROJECT OFFERING | B6: 28755920 | C6: 64180124 | D6: 26908636 | E6: 166463408 | F6: 38219779 | G6: 47490621 | H6: 172134500 | I6: 53238738 | J6: 221034851 | K6: 169852187 | L6: 49827146 | M6: 59953718 | N6: =M6+L6+K6+J6+I6+H6+G6+F6+E6+D6+C6+B6 -> 1098059628
A7: SACRIFICE | B7: 161338791 | C7: 107466417 | D7: 38098950 | E7: 42639956 | F7: 9894400 | G7: 19470245 | H7: 61766568 | I7: 110410500 | J7: 93834040 | K7: 10412342 | L7: 12416780 | M7: 10710000 | N7: =M7+L7+K7+J7+I7+H7+G7+F7+E7+D7+C7+B7 -> 678458989
A8: SALE OF MATERIAL OFFERING | B8: 0 | C8: 0 | D8: 0 | E8: 0 | F8: 0 | G8: 0 | H8: 0 | I8: 0 | J8: 0 | K8: 0 | L8: 0 | M8: 0 | N8: =M8+L8+K8+J8+I8+H8+G8+F8+E8+D8+C8+B8 -> 0
A9: STUDIO-RESOURCE MATERIAL | B9: 2063734 | C9: 832564 | D9: 870678 | E9: 733479 | F9: 718601 | G9: 0 | H9: 6499411 | I9: 1551635 | J9: 1697973 | K9: 721783 | L9: 528521 | M9: 380803 | N9: =M9+L9+K9+J9+I9+H9+G9+F9+E9+D9+C9+B9 -> 16599182
A10: THANKSGIVING OFFERING | B10: 7030940 | C10: 7118640 | D10: 2735901 | E10: 7963104 | F10: 736500 | G10: 1179820 | H10: 1043199 | I10: 4038502 | J10: 3190775 | K10: 981400 | L10: 3100275 | M10: 14756976 | N10: =M10+L10+K10+J10+I10+H10+G10+F10+E10+D10+C10+B10 -> 53876032
A11: TITHE | B11: 18686413 | C11: 14989392 | D11: 15844410 | E11: 19904653 | F11: 14404981 | G11: 13889670 | H11: 27035344 | I11: 17119300 | J11: 16420873 | K11: 15114697 | L11: 14144976 | M11: 31400509 | N11: =M11+L11+K11+J11+I11+H11+G11+F11+E11+D11+C11+B11 -> 218955218
A12: TMA FEE | B12: 0 | C12: 0 | D12: 0 | E12: 2000 | F12: 0 | G12: 0 | H12: 0 | I12: 0 | J12: 0 | K12: 0 | L12: 0 | M12: 0 | N12: =M12+L12+K12+J12+I12+H12+G12+F12+E12+D12+C12+B12 -> 2000
A13: TMP BENIN | B13: 284367 | C13: 385324 | D13: 235000 | E13: 230500 | F13: 305106 | G13: 247742 | H13: 217830 | I13: 189600 | J13: 165968 | K13: 315773 | L13: 365977 | M13: 477826 | N13: =M13+L13+K13+J13+I13+H13+G13+F13+E13+D13+C13+B13 -> 3421013
A14: TMP OGBOMOSO | B14: 0 | C14: 606000 | D14: 500000 | E14: 823000 | F14: 606000 | G14: 680000 | H14: 592000 | I14: 0 | J14: 501000 | K14: 551000 | L14: 517000 | M14: 1320000 | N14: =M14+L14+K14+J14+I14+H14+G14+F14+E14+D14+C14+B14 -> 6696000
A15: TMP SAPELE | B15: 0 | C15: 196000 | D15: 414000 | E15: 343000 | F15: 56586 | G15: 138000 | H15: 150490 | I15: 0 | J15: 103000 | K15: 0 | L15: 339603 | M15: 184772 | N15: =M15+L15+K15+J15+I15+H15+G15+F15+E15+D15+C15+B15 -> 1925451
... A18: TMP LAGOS | B18: 0 | C18: 0 | D18: 0 | E18: 0 | F18: 0 | G18: 0 | H18: 0 | I18: 0 | J18: 0 | K18: 0 | L18: 300000 | M18: 1057000 | N18: =M18+L18+K18+J18+I18+H18+G18+F18+E18+D18+C18+B18 -> 1357000
A19: Total Revenues | B19: =SUM(B2:B18) -> 2.7416592e+08 | C19: =SUM(C2:C18) -> 2.1476169e+08 | D19: =SUM(D2:D18) -> 1.0850035e+08 | E19: =SUM(E2:E18) -> 2.6049652e+08 | F19: =SUM(F2:F18) -> 86319844 | G19: =SUM(G2:G18) -> 1.0513186e+08 | H19: =SUM(H2:H18) -> 3.0993043e+08 | I19: =SUM(I2:I18) -> 2.1582307e+08 | ... N19: =SUM(N2:N18) -> 2.3454035e+09
A21: Other Income (B)
A22: Interest Received from FX | B22: 0 | C22: 0 | D22: 0 | E22: 0 | F22: 0 | G22: 0 | H22: 0 | I22: 0 | K22: 0 | L22: 0 | M22: 0 | N22: =SUM(B22:M22) -> 0
A23: TMP Ebrumede | B23: 102000 | C23: 0 | D23: 0 | E23: 0 | F23: 0 | G23: 0 | H23: 0 | I23: 0 | J23: 0 | K23: 53200 | L23: 100700 | M23: 80700 | N23: =SUM(B23:M23) -> 336600
A24: TMP Orhuwhorun | B24: 0 | C24: 0 | D24: 0 | E24: 0 | F24: 430000 | G24: 0 | H24: 0 | I24: 0 | J24: 0 | K24: 0 | L24: 170192 | M24: 200000 | N24: =SUM(B24:M24) -> 800192
A25: TMP Osubi | B25: 0 | C25: 0 | D25: 114000 | E25: 149000 | F25: 108000 | G25: 88000 | H25: 168000 | I25: 108000 | J25: 79000 | K25: 69000 | L25: 129000 | M25: 118000 | N25: =SUM(B25:M25) -> 1130000
A26: TMP Otokutu | B26: 0 | C26: 0 | D26: 175182 | E26: 112256 | F26: 0 | G26: 90210 | H26: 108244 | I26: 0 | J26: 113519 | K26: 48206 | L26: 0 | M26: 78668 | N26: =SUM(B26:M26) -> 726285
A27: TMP Ubeji | B27: 0 | C27: 0 | D27: -23871 | E27: 117918 | F27: 0 | G27: 0 | H27: 0 | I27: 0 | J27: 0 | K27: 0 | L27: 0 | M27: 0 | N27: =SUM(B27:M27) -> 94047
A28: TMP Udu | B28: 0 | C28: 0 | D28: 0 | E28: 80000 | F28: 72000 | G28: 36000 | H28: 0 | I28: 0 | J28: 156000 | K28: 131300 | L28: 113000 | M28: 206000 | N28: =SUM(B28:M28) -> 794300
A29: TMP Ugbuwangue | B29: 0 | C29: 0 | D29: 318000 | E29: 0 | F29: 146878 | G29: 0 | H29: 0 | I29: 0 | J29: 0 | K29: 0 | L29: 0 | M29: 0 | N29: =SUM(B29:M29) -> 464878
A30: TMP Ughoton | B30: 0 | C30: 0 | D30: 241380 | E30: 112500 | F30: 120000 | G30: 86000 | H30: 0 | I30: 0 | J30: 0 | K30: 0 | L30: 49100 | M30: 85740 | N30: =SUM(B30:M30) -> 694720
A31: TMP Warri Central | B31: 0 | C31: 0 | D31: 0 | E31: 655000 | F31: 350000 | G31: 370000 | H31: 350000 | I31: 220000 | J31: 210000 | K31: 170000 | L31: 190000 | M31: 110000 | N31: =SUM(B31:M31) -> 2625000
A32: TMP Warri G.R.A | B32: 0 | C32: 0 | D32: 0 | E32: 25000 | F32: 0 | G32: 0 | H32: 0 | I32: 0 | J32: 17000 | K32: 0 | L32: 21600 | M32: 46100 | N32: =SUM(B32:M32) -> 109700
A33: Total for other Income | B33: =SUM(B22:B32) -> 102000 | C33: =SUM(C22:C32) -> 0 | D33: =SUM(D22:D32) -> 824691 | E33: =SUM(E22:E32) -> 1251674 | F33: =SUM(F22:F32) -> 1226878 | G33: =SUM(G22:G32) -> 670210 | H33: =SUM(H22:H32) -> 626244 | I33: =SUM(I22:I32) -> 328000 | ... M33: =SUM(M22:M32) -> 925208 | N33: =SUM(B33:M33) -> 7775722
A35: TOTAL REVENUE | B35: =B19+B33 -> 2.7426792e+08 | C35: =C19+C33 -> 2.1476169e+08 | D35: =D19+D33 -> 1.0932504e+08 | E35: =E19+E33 -> 2.617482e+08 | F35: =F19+F33 -> 87546722 | G35: =G19+G33 -> 1.0580207e+08 | H35: =H19+H33 -> 3.1055667e+08 | I35: =I19+I33 -> 2.1615107e+08 | ... N35: =N19+N33 -> 2.3531792e+09
A37: Expenditure (C)
A38: Advert & Publicity | B38: 6815250 | C38: 7967350 | D38: 11808610 | E38: 8027430 | F38: 6992900 | G38: 9540106 | H38: 5046786 | I38: 10365910 | J38: 15005340 | K38: 5344050 | L38: 8974672 | M38: 4193000 | N38: =SUM(B38:M38) -> 100081404
A39: Allowances and Bonus | B39: 0 | C39: 0 | D39: 0 | E39: 0 | F39: 900000 | G39: 1730000 | H39: 1380000 | I39: 650000 | J39: 1370000 | K39: 960000 | L39: 0 | M39: 0 | N39: =SUM(B39:M39) -> 6990000
A40: Bank Charges | B40: 455349 | C40: 533148 | D40: 362988 | E40: 572285 | F40: 306134 | G40: 263771 | H40: 813050 | I40: 427870 | J40: 622063 | K40: 426060 | L40: 278835 | M40: 394433 | N40: =SUM(B40:M40) -> 5455986
A41: Chairs/Canopies Rent | B41: 2830000 | C41: 2660000 | D41: 3520000 | E41: 3608000 | F41: 300000 | G41: 2090000 | H41: 8735000 | I41: 4070000 | J41: 0 | K41: 0 | L41: 0 | M41: 0 | N41: =SUM(B41:M41) -> 27813000
A42: Church Service Expense | B42: 400000 | C42: 350000 | D42: 450000 | E42: 400000 | F42: 450000 | G42: 354000 | H42: 492000 | I42: 490000 | J42: 430000 | K42: 405000 | L42: 530000 | M42: 441000 | N42: =SUM(B42:M42) -> 5192000
A43: Consumables | B43: 0 | C43: 1267060 | D43: 0 | E43: 795820 | F43: 712000 | G43: 426160 | H43: 0 | I43: 218860 | J43: 554720 | K43: 0 | L43: 845410 | M43: 348340 | N43: =SUM(B43:M43) -> 5168370
A44: Diesel | B44: 7560000 | C44: 6796000 | D44: 6220000 | E44: 9720000 | F44: 7560000 | G44: 6570000 | H44: 9720000 | I44: 9140000 | J44: 4900000 | K44: 9220000 | L44: 6722500 | M44: 8720000 | N44: =SUM(B44:M44) -> 92848500
A45: Electricity | B45: 50000 | C45: 50000 | D45: 228000 | E45: 50000 | F45: 100000 | G45: 50000 | H45: 100000 | I45: 100000 | J45: 260000 | K45: 0 | L45: 200000 | M45: 150000 | N45: =SUM(B45:M45) -> 1338000
A46: Entertainment | B46: 3908100 | C46: 1045000 | D46: 1853900 | E46: 1961000 | F46: 669000 | G46: 1255200 | H46: 1187700 | I46: 413000 | J46: 1101000 | K46: 245000 | L46: 1103900 | M46: 180000 | N46: =SUM(B46:M46) -> 14922800
A47: Forex Expense | B47: 0 | C47: 0 | D47: 0 | E47: 2000000 | F47: 0 | G47: 0 | H47: 0 | I47: 0 | J47: 0 | K47: 1788000 | L47: 0 | M47: 0 | N47: =SUM(B47:M47) -> 3788000
A48: Fuel | B48: 3251000 | C48: 2507000 | D48: 2650000 | E48: 3418000 | F48: 2458000 | G48: 1785000 | H48: 2131000 | I48: 3055000 | J48: 2338000 | K48: 2484000 | L48: 2045000 | M48: 2226000 | N48: =SUM(B48:M48) -> 30348000
A49: Generator Repairs & Mtce | B49: 123000 | C49: 320000 | D49: 1945400 | E49: 725000 | F49: 166500 | G49: -521500 | H49: 511800 | I49: 0 | J49: 0 | K49: 85000 | L49: 124000 | M49: 0 | N49: =SUM(B49:M49) -> 3479200
... A68: Security | B68: 1717000 | C68: 912500 | D68: 3148000 | E68: 1173000 | F68: 662000 | G68: 1336000 | H68: 6945000 | I68: 1392900 | J68: 1673000 | K68: 1281000 | L68: 0 | M68: 1844000 | N68: =SUM(B68:M68) -> 22084400
A69: Studio | B69: 0 | C69: 0 | D69: 0 | E69: 0 | F69: 0 | G69: 0 | H69: 0 | I69: 0 | J69: 0 | K69: 0 | L69: - | M69: 0 | N69: =SUM(B69:M69) -> 0
A70: Telephone & Internet | B70: 180000 | C70: 380000 | D70: 360000 | E70: 90000 | F70: 330000 | G70: 440000 | H70: 10727634 | I70: 365000 | J70: 0 | K70: 0 | L70: 455000 | M70: 781000 | N70: =SUM(B70:M70) -> 14108634
A71: Transport & Travelling | B71: 16387320 | C71: 24885910 | D71: 26859350 | E71: 35786830 | F71: 16801100 | G71: 23476000 | H71: 43535500 | I71: 21534319 | J71: 46228610 | K71: 7139000 | L71: 14358000 | M71: 47349200 | N71: =SUM(B71:M71) -> 324341139
A72: Vehicle Maintenance | B72: 978000 | C72: 10000 | D72: 0 | E72: 0 | F72: 185300 | G72: 705100 | H72: 303500 | I72: 384000 | J72: 346500 | K72: 80000 | L72: 157000 | M72: 0 | N72: =SUM(B72:M72) -> 3149400
A73: Video Coverage | B73: 3381000 | C73: 2707600 | D73: 1390000 | E73: 2069000 | F73: 397000 | G73: 730000 | H73: 2415350 | I73: 177000 | J73: 372000 | K73: 1850000 | L73: 0 | M73: 1680000 | N73: =SUM(B73:M73) -> 17168950
A74: Welfare | B74: 0 | C74: 1871000 | D74: 150000 | E74: 1541900 | F74: 3650000 | G74: 500000 | H74: 3421800 | I74: 749000 | J74: 6958050 | K74: 1779801 | L74: 0 | M74: 2360000 | N74: =SUM(B74:M74) -> 22981551
A75: Kingdom Investment | B75: 25000000 | C75: 25000000 | D75: 5000000 | E75: 0 | F75: 10000000 | G75: 0 | H75: 53240000 | I75: 20000000 | J75: 5000000 | K75: 55465000 | L75: 21000000 | M75: 0 | N75: =SUM(B75:M75) -> 219705000
A77: Total Expenses | B77: =ROUND(SUBTOTAL(9, B37:B76), 5) -> 102392029 | C77: =ROUND(SUBTOTAL(9, C37:C76), 5) -> 105363063 | D77: =ROUND(SUBTOTAL(9, D37:D76), 5) -> 88415293 | E77: =ROUND(SUBTOTAL(9, E37:E76), 5) -> 126378265 | F77: =ROUND(SUBTOTAL(9, F37:F76), 5) -> 75342684 | G77: =ROUND(SUBTOTAL(9, G37:G76), 5) -> 90927037 | H77: =ROUND(SUBTOTAL(9, H37:H76), 5) -> 212925000 | I77: =ROUND(SUBTOTAL(9, I37:I76), 5) -> 113296592 | ... M77: =ROUND(SUBTOTAL(9, M37:M76), 5) -> 126453503 | N77: =SUM(N38:N76) -> 1523001287
A79: Net Income | B79: =-(ROUND(-B35+B77, 5)) -> 1.7187589e+08 | C79: =-(ROUND(-C35+C77, 5)) -> 1.0939862e+08 | D79: =-(ROUND(-D35+D77, 5)) -> 20909748 | E79: =-(ROUND(-E35+E77, 5)) -> 1.3536993e+08 | F79: =-(ROUND(-F35+F77, 5)) -> 12204038 | G79: =-(ROUND(-G35+G77, 5)) -> 14875031 | H79: =-(ROUND(-H35+H77, 5)) -> 97631671 | I79: =I35-I77 -> 1.0285448e+08 | J79: =-(ROUND(-J35+J77, 5)) -> 1.0558085e+08 | K79: =-(ROUND(-K35+K77, 5)) -> 86439669 | L79: =-(ROUND(-L35+L77, 5)) -> 12560738 | M79: =-(ROUND(-M35+M77, 5)) -> 18307205 | N79: =N35-N77 -> 8.3017791e+08
A81: Cash Flow (C)
A82: Building | B82: -167055500 | C82: -103477500 | D82: -15660000 | E82: -130072000 | F82: -3134000 | G82: -10062500 | H82: -85552500 | I82: -93052000 | J82: -101940000 | K82: -82500000 | L82: -7062500 | M82: -11062500 | N82: =SUM(B82:M82) -> -810631000
A83: Equipment | B83: 0 | C83: 0 | D83: 0 | E83: 0 | F83: -6196600 | G83: 0 | H83: 0 | I83: 0 | J83: 0 | L83: 0 | M83: 0 | N83: =SUM(B83:M83) -> -6196600
A84: Furniture and Fittings | B84: 0 | C84: 0 | D84: -474600 | E84: 0 | F84: 0 | G84: 0 | H84: -2730000 | I84: -2900000 | J84: 0 | K84: 0 | L84: 0 | M84: 0 | N84: =SUM(B84:M84) -> -6104600
A85: Land | B85: 0 | C85: 0 | D85: 0 | E85: 0 | F85: 0 | G85: 0 | H85: 0 | I85: 0 | J85: 0 | K85: 0 | L85: 0 | M85: 0 | N85: =SUM(B85:M85) -> 0
A86: Motor Vehicles | B86: 0 | C86: 0 | D86: 0 | E86: 0 | F86: 0 | G86: 0 | H86: 0 | I86: 0 | J86: 0 | K86: 0 | L86: 0 | M86: 0 | N86: =SUM(B86:M86) -> 0
A87: Current Liabilities | B87: 0 | C87: 0 | D87: 531511.91 | E87: 0 | F87: 0 | G87: 0 | H87: 0 | I87: 10734.8 | J87: 0 | K87: 0 | L87: 0 | M87: 0 | N87: 0
A88: UBA | B88: 0 | C88: 0 | D88: 0 | E88: 0 | F88: 0 | G88: 0 | H88: 0 | I88: 0 | J88: 0 | K88: 0 | L88: 37750.52 | M88: 0 | N88: 0
A89: GTB | B89: 0 | C89: 0 | D89: 0 | E89: 0 | F89: 0 | G89: 55802.64 | H89: 0 | I89: 0 | J89: 0 | K89: 0 | L89: 0 | M89: 0 | N89: 0
A90: Zenith Bank (Main) | B90: 0 | C90: 0 | D90: 0 | E90: 0 | F90: 55305.81 | G90: -55305 | H90: 33867.71 | I90: 20064.4 | J90: 0 | K90: 0 | L90: 0 | M90: 0 | N90: 0
A91: Zenith Bank Partnership | B91: 0 | C91: 0 | D91: 0 | E91: 0 | F91: 0 | G91: 0 | H91: 0 | I91: 0 | J91: 0 | K91: 0 | L91: 0 | M91: 0 | N91: =SUM(B91:M91) -> 0
A92: Access Bank | B92: 0 | C92: 0 | D92: 0 | E92: 0 | F92: 0 | G92: 0 | H92: 0 | I92: 0 | J92: 868.88 | K92: 0 | L92: 0 | M92: 0 | N92: 0
A93: GTB Domiciliary | B93: 0 | C93: 0 | D93: 0 | E93: 0 | F93: 0 | G93: 0 | H93: 0 | I93: 0 | J93: 10734.8 | K93: 10734.8 | L93: 22452.63 | M93: 0 | N93: 0
A94: Zenith Bank Remittance | B94: 5044 | C94: 0 | D94: 0 | E94: 0 | F94: 0 | G94: 68422.9 | H94: 0 | I94: 0 | J94: 2422.85 | K94: 1817.35 | L94: 0 | M94: 0 | N94: 0
A96: Net cash used in Investing | B96: =B82+B83+B84+B86 -> -167055500 | C96: =C82+C83+C84+C86 -> -103477500 | D96: -15603088 | E96: =E82+E83+E84+E86+E85 -> -130072000 | F96: =F82+F83+F84+F86+F85 -> -9330600 | G96: =G82+G83+G84+G86+G85 -> -10062500 | H96: =H82+H83+H84+H86+H85 -> -88282500 | I96: =I82+I83+I84+I86+I85+I94+I87+I90 -> -95921201 | J96: =J82+J83+J84+J86+J85+J94+J92+J93 -> -1.0192597e+08 | K96: =K82+K83+K84+K86+K85+K94+K93 -> -82487448 | L96: =L82+L83+L84+L86+L85+L94+L93+L88 -> -7002296.9 | M96: -11062500 | N96: =SUM(N82:N95) -> -822932200
A98: Net Surplus or Deficit | B98: =B79+B96 -> 4820388.7 | C98: =C79+C96 -> 5921124.5 | D98: =D79+D96 -> 5306660.4 | E98: =E79+E96 -> 5297932.8 | F98: =F79+F96 -> 2873437.9 | G98: 4881451.9 | H98: =H79+H96 -> 9349170.9 | I98: =I79+I96 -> 6933275.2 | J98: =J79+J96 -> 3654879.5 | K98: =K79+K96 -> 3952221.5 | L98: =L79+L96 -> 5558441.1 | M98: =M79+M96 -> 7244705.1 | N98: =N79+N96 -> 7245705.7
C104: 181707854
C105: 173184384
C106: =C104-C105 -> 8523470
D108: -31009712
F111: =ROUND(SUBTOTAL(9, F64:F110), 5) -> 36354482

Sheet January Financial Statement
A1: The Master's Place International Church, Headquaters -Warri
A2: Income & Expenditure Statement
A3: 45688
A5: DESCRIPTION | B5: Balance B/F | C5: January | D5: YEAR TO DATE
A6: Opening Balance | D6: =B6+C6 -> 0
A7: Income (A)
A8: Home Connect Offering | D8: =B8+C8 -> 0
A9: OFFERING | D9: =B9+C9 -> 0
A10: PROJECT OFFERING | D10: =B10+C10 -> 0
A11: SACRIFICE | D11: =B11+C11 -> 0
A12: STUDIO-RESOURCE MATERIAL | D12: =B12+C12 -> 0
A13: SALES OF MATERIAL OFFERING | D13: =B13+C13 -> 0
A14: THANKSGIVING OFFERING | D14: =B14+C14 -> 0
A15: TITHE | D15: =B15+C15 -> 0
A16: TMA FEE | D16: =B16+C16 -> 0
A17: TMP BENIN | D17: =B17+C17 -> 0
A18: TMP OGBOMOSO | D18: =B18+C18 -> 0
A19: TMP SAPELE | D19: =B19+C19 -> 0
A20: TMP UGHELI | D20: =B20+C20 -> 0
A21: Total Revenues | B21: =SUM(B6:B15) -> 0 | C21: =SUM(C6:C20) -> 0 | D21: =B21+C21 -> 0
A23: Other Income (B)
A24: Interest Received from FX | C24: 0 | D24: =B24+C24 -> 0
A25: TMP Ebrumede | C25: 102000 | D25: =B25+C25 -> 102000
A26: TMP Orhuwhorun | C26: 0 | D26: =B26+C26 -> 0
A27: TMP Osubi | C27: 0 | D27: =B27+C27 -> 0
A28: TMP Otokutu | C28: 0 | D28: =B28+C28 -> 0
A29: TMP Ubeji | C29: 0 | D29: =B29+C29 -> 0
A30: TMP Udu | C30: 0 | D30: =B30+C30 -> 0
A31: TMP Ugbuwangue | C31: 0 | D31: =B31+C31 -> 0
A32: TMP Ughoton | C32: 0 | D32: =B32+C32 -> 0
A33: TMP Warri Central | C33: 0 | D33: =B33+C33 -> 0
A34: TMP Warri G.R.A | C34: 0 | D34: =B34+C34 -> 0
A35: Total for other Income | B35: =SUM(B24:B34) -> 0 | C35: =SUM(C24:C34) -> 102000 | D35: =SUM(D24:D34) -> 102000
A37: TOTAL REVENUE | B37: =B21+B35 -> 0 | C37: =C21+C35 -> 102000 | D37: =D21+D35 -> 102000
A40: Expenditure (C)
A41: Advert & Publicity | C41: 6815250 | D41: =B41+C41 -> 6815250
A42: Allowances and Bonus | C42: 0 | D42: =B42+C42 -> 0
A43: Bank Charges | C43: 455349 | D43: =B43+C43 -> 455349
A44: Chairs/Canopies Rent | C44: 2830000 | D44: =B44+C44 -> 2830000
A45: Church Service Expense | C45: 400000 | D45: =B45+C45 -> 400000
A46: Consumables | C46: 0 | D46: =B46+C46 -> 0
A47: Diesel | C47: 7560000 | D47: =B47+C47 -> 7560000
A48: Electricity | C48: 50000 | D48: =B48+C48 -> 50000
A49: Entertainment | C49: 3908100 | D49: =B49+C49 -> 3908100
A50: Forex Expense | C50: 0 | D50: =B50+C50 -> 0
A51: Fuel | C51: 3251000 | D51: =B51+C51 -> 3251000
A52: Generator Repairs & Mtce | C52: 123000 | D52: =B52+C52 -> 123000
... A76: Kingdom Investment | C76: 25000000 | D76: =B76+C76 -> 25000000
A77: Total Expenses | B77: =ROUND(SUBTOTAL(9, B40:B75), 5) -> 0 | C77: =ROUND(SUBTOTAL(9, C40:C76), 5) -> 102392029 | D77: =B77+C77 -> 102392029
A79: Net Income | B79: =(ROUND(B37-B77, 5)) -> 0 | C79: =C37-C77 -> -102290029 | D79: =(ROUND(D37-D77, 5)) -> -102290029
A81: Cash Flow (C)
A82: Building | C82: -167055500 | D82: =B82+C82 -> -167055500
A83: Equipment | C83: 0 | D83: =B83+C83 -> 0
A84: Furniture and Fittings | C84: 0 | D84: =B84+C84 -> 0
A85: Land | C85: 0 | D85: =B85+C85 -> 0
A86: Motor Vehicles | C86: 0 | D86: =B86+C86 -> 0
A87: Currrent liabilities | C87: 5044
A89: Net cash used in Investing | B89: =B83+B84+B86+B82 -> 0 | C89: =C83+C84+C86+C82 -> -167055500 | D89: =B89+C89 -> -167055500
A92: Net Surplus or Deficit | B92: =B79+B89 -> 0 | C92: =C79+C89 -> -269345529 | D92: =D79+D89 -> -269345529

Sheet February Financial Statement
A1: The Master's Place International Church, Headquaters -Warri
A2: Income & Expenditure Statement
A3: 29/02/2025
A5: DESCRIPTION | B5: Balance B/F | C5: February | D5: YEAR TO DATE
A6: Opening Balance | B6: 32971800 | C6: 4820388.5 | D6: =B6+C6 -> 37792188
A7: Income (A)
A8: Home Connect Offering | B8: 222750 | C8: 71000 | D8: =B8+C8 -> 293750
A9: OFFERING | B9: 22085703 | C9: 13593838 | D9: =B9+C9 -> 35679541
A10: PROJECT OFFERING | B10: 28755920 | C10: 64180124 | D10: =B10+C10 -> 92936044
A11: SACRIFICE | B11: 161338791 | C11: 107466417 | D11: =B11+C11 -> 268805208
A12: STUDIO-RESOURCE MATERIAL | B12: 2063734 | C12: 832564 | D12: =B12+C12 -> 2896298
A13: SALES OF MATERIAL OFFERING | B13: 0 | C13: 0 | D13: =B13+C13 -> 0
A14: THANKSGIVING OFFERING | B14: 7030940 | C14: 7118640 | D14: =B14+C14 -> 14149580
A15: TITHE | B15: 18686413 | C15: 14989392 | D15: =B15+C15 -> 33675805
A16: TMA FEE | B16: 0 | C16: 0 | D16: =B16+C16 -> 0
A17: TMP BENIN | B17: 284367 | C17: 385324 | D17: =B17+C17 -> 669691
A18: TMP OGBOMOSO | B18: 0 | C18: 606000 | D18: =B18+C18 -> 606000
A19: TMP SAPELE | B19: 0 | C19: 196000 | D19: =B19+C19 -> 196000
A20: TMP UGHELI | B20: 725500 | C20: 502000 | D20: =B20+C20 -> 1227500
A21: Total Revenues | B21: =SUM(B6:B20) -> 2.7416592e+08 | C21: =SUM(C6:C20) -> 2.1476169e+08 | D21: =B21+C21 -> 4.8892761e+08
A23: Other Income (B)
A24: Interest Received from FX | B24: 0 | C24: 0 | D24: =B24+C24 -> 0
A25: TMP Ebrumede | B25: 102000 | C25: 0 | D25: =B25+C25 -> 102000
A26: TMP Orhuwhorun | B26: 0 | C26: 0 | D26: =B26+C26 -> 0
A27: TMP Osubi | B27: 0 | C27: 0 | D27: =B27+C27 -> 0
A28: TMP Otokutu | B28: 0 | C28: 0 | D28: =B28+C28 -> 0
A29: TMP Ubeji | B29: 0 | C29: 0 | D29: =B29+C29 -> 0
A30: TMP Udu | B30: 0 | C30: 0 | D30: =B30+C30 -> 0
A31: TMP Ugbuwangue | B31: 0 | C31: 0 | D31: =B31+C31 -> 0
A32: TMP Ughoton | B32: 0 | C32: 0 | D32: =B32+C32 -> 0
A33: TMP Warri Central | B33: 0 | C33: 0 | D33: =B33+C33 -> 0
A34: TMP Warri G.R.A | B34: 0 | C34: 0 | D34: =B34+C34 -> 0
A35: Total for other Income | B35: =SUM(B24:B34) -> 102000 | C35: =SUM(C24:C34) -> 0 | D35: =SUM(D24:D34) -> 102000
A37: TOTAL REVENUE | B37: =B21+B35 -> 2.7426792e+08 | C37: =C21+C35 -> 2.1476169e+08 | D37: =D21+D35 -> 4.8902961e+08
A40: Expenditure (C)
A41: Advert & Publicity | B41: 6815250 | C41: 7967350 | D41: =B41+C41 -> 14782600
A42: Allowances and Bonus | B42: 0 | C42: 0 | D42: =B42+C42 -> 0
A43: Bank Charges | B43: 455349 | C43: 533148 | D43: =B43+C43 -> 988497
A44: Chairs/Canopies Rent | B44: 2830000 | C44: 2660000 | D44: =B44+C44 -> 5490000
A45: Church Service Expense | B45: 400000 | C45: 350000 | D45: =B45+C45 -> 750000
A46: Consumables | B46: 0 | C46: 1267060 | D46: =B46+C46 -> 1267060
A47: Diesel | B47: 7560000 | C47: 6796000 | D47: =B47+C47 -> 14356000
A48: Electricity | B48: 50000 | C48: 50000 | D48: =B48+C48 -> 100000
A49: Entertainment | B49: 3908100 | C49: 1045000 | D49: =B49+C49 -> 4953100
A50: Forex Expense | B50: 0 | C50: 0 | D50: =B50+C50 -> 0
A51: Fuel | B51: 3251000 | C51: 2507000 | D51: =B51+C51 -> 5758000
A52: Generator Repairs & Mtce | B52: 123000 | C52: 320000 | D52: =B52+C52 -> 443000
... A76: Kingdom Investment | B76: 25000000 | C76: 25000000 | D76: =B76+C76 -> 50000000
A77: Total Expenses | B77: =ROUND(SUBTOTAL(9, B40:B76), 5) -> 102392029 | C77: =ROUND(SUBTOTAL(9, C40:C76), 5) -> 105363063 | D77: =B77+C77 -> 207755092
A79: Net Income | B79: =B37-B77 -> 1.7187589e+08 | C79: =C37-C77 -> 1.0939862e+08 | D79: =D37-D77 -> 2.8127451e+08
A81: Cash Flow (C)
A82: Building | B82: -167055500 | C82: -103477500 | D82: =B82+C82 -> -270533000
A83: Equipment | B83: 0 | C83: 0 | D83: =B83+C83 -> 0
A84: Furniture and Fittings | B84: 0 | C84: 0 | D84: =B84+C84 -> 0
A85: Land | B85: 0 | C85: 0 | D85: =B85+C85 -> 0
A86: Motor Vehicles | B86: 0 | C86: 0 | D86: =B86+C86 -> 0
A87: current liabilities | B87: 5044 | C87: 0
A89: Net cash used in Investing | B89: =B83+B84+B86+B82 -> -167055500 | C89: =C83+C84+C86+C82 -> -103477500 | D89: =B89+C89 -> -270533000
A92: Net Surplus or Deficit | B92: =B79+B89 -> 4820388.7 | C92: =C79+C89 -> 5921124.5 | D92: =D79+D89 -> 10741513

Sheet March Financial Statement
A1: The Master's Place International Church, Headquaters -Warri
A2: Income & Expenditure Statement
A3: 45747
A5: DESCRIPTION | B5: Balance B/F | C5: March | D5: YEAR TO DATE
A6: Opening Balance | B6: 37792188 | C6: 5921123.5 | D6: =B6+C6 -> 43713312
A7: Income (A)
A8: Home Connect Offering | B8: 293750 | C8: 68400 | D8: =B8+C8 -> 362150
A9: OFFERING | B9: 35679541 | C9: 16251845 | D9: =B9+C9 -> 51931386
A10: PROJECT OFFERING | B10: 92936044 | C10: 26908636 | D10: =B10+C10 -> 119844680
A11: SACRIFICE | B11: 268805208 | C11: 38098950 | D11: =B11+C11 -> 306904158
A12: STUDIO-RESOURCE MATERIAL | B12: 2896298 | C12: 870678 | D12: =B12+C12 -> 3766976
A13: SALES OF MATERIAL OFFERING | B13: 0 | D13: =B13+C13 -> 0
A14: THANKSGIVING OFFERING | B14: 14149580 | C14: 2735901 | D14: =B14+C14 -> 16885481
A15: TITHE | B15: 33675805 | C15: 15844410 | D15: =B15+C15 -> 49520215
A16: TMA FEE | B16: 0 | C16: 0 | D16: =B16+C16 -> 0
A17: TMP BENIN | B17: 669691 | C17: 235000 | D17: =B17+C17 -> 904691
A18: TMP OGBOMOSO | B18: 606000 | C18: 500000 | D18: =B18+C18 -> 1106000
A19: TMP SAPELE | B19: 196000 | C19: 414000 | D19: =B19+C19 -> 610000
A20: TMP PORTHARCOURT | B20: 0 | C20: 0
A21: TMP UGHELI | B21: 1227500 | C21: 651406 | D21: =B21+C21 -> 1878906
A22: Total Revenues | B22: =B6+B8+B9+B10+B12+B11+B14+B15+B17+B18+B19+B21 -> 4.8892761e+08 | C22: =SUM(C6:C21) -> 1.0850035e+08 | D22: =B22+C22 -> 5.9742795e+08
A24: Other Income (B)
A25: Interest Received from FX | B25: 0 | C25: 0 | D25: =B25+C25 -> 0
A26: TMP Ebrumede | B26: 102000 | C26: 0 | D26: =B26+C26 -> 102000
A27: TMP Orhuwhorun | B27: 0 | C27: 0 | D27: =B27+C27 -> 0
A28: TMP Osubi | B28: 0 | C28: 114000 | D28: =B28+C28 -> 114000
A29: TMP Otokutu | B29: 0 | C29: 175182 | D29: =B29+C29 -> 175182
A30: TMP Ubeji | B30: 0 | C30: -23871 | D30: =B30+C30 -> -23871
A31: TMP Udu | B31: 0 | C31: 0 | D31: =B31+C31 -> 0
A32: TMP Ugbuwangue | B32: 0 | C32: 318000 | D32: =B32+C32 -> 318000
A33: TMP Ughoton | B33: 0 | C33: 241380 | D33: =B33+C33 -> 241380
A34: TMP Warri Central | B34: 0 | C34: 0 | D34: =B34+C34 -> 0
A35: TMP Warri G.R.A | B35: 0 | C35: 0 | D35: =B35+C35 -> 0
A36: Total for other Income | B36: =SUM(B25:B35) -> 102000 | C36: =SUM(C25:C35) -> 824691 | D36: =SUM(D25:D35) -> 926691
A38: TOTAL REVENUE | B38: =B22+B36 -> 4.8902961e+08 | C38: =C22+C36 -> 1.0932504e+08 | D38: =D22+D36 -> 5.9835465e+08
A41: Expenditure (C)
A42: Advert & Publicity | B42: 14782600 | C42: 11808610 | D42: =B42+C42 -> 26591210
A43: Allowances and Bonus | B43: 0 | C43: 0 | D43: =B43+C43 -> 0
A44: Bank Charges | B44: 988497 | C44: 362988 | D44: =B44+C44 -> 1351485
A45: Chairs/Canopies Rent | B45: 5490000 | C45: 3520000 | D45: =B45+C45 -> 9010000
A46: Church Service Expense | B46: 750000 | C46: 450000 | D46: =B46+C46 -> 1200000
A47: Consumables | B47: 1267060 | C47: 0 | D47: =B47+C47 -> 1267060
A48: Diesel | B48: 14356000 | C48: 6220000 | D48: =B48+C48 -> 20576000
A49: Electricity | B49: 100000 | C49: 228000 | D49: =B49+C49 -> 328000
A50: Entertainment | B50: 4953100 | C50: 1853900 | D50: =B50+C50 -> 6807000
A51: Forex Expense | B51: 0 | C51: 0 | D51: =B51+C51 -> 0
A52: Fuel | B52: 5758000 | C52: 2650000 | D52: =B52+C52 -> 8408000
A53: Generator Repairs & Mtce | B53: 443000 | C53: 1945400 | D53: =B53+C53 -> 2388400
... A79: Kingdom Investment | B79: 50000000 | C79: 5000000 | D79: =B79+C79 -> 55000000
A80: Total Expenses | B80: =ROUND(SUBTOTAL(9, B41:B79), 5) -> 207755092 | C80: =ROUND(SUBTOTAL(9, C41:C79), 5) -> 88415293 | D80: =B80+C80 -> 296170385
A82: Net Income | B82: =(ROUND(B38-B80, 5)) -> 2.8127451e+08 | C82: =C38-C80 -> 20909748 | D82: =(ROUND((D6+D38)-D80, 5)) -> 3.4589757e+08
A84: Cash Flow (C)
A85: Building | B85: -270533000 | C85: -15660000 | D85: =B85+C85 -> -286193000
A86: Equipment | B86: 0 | C86: 0 | D86: =B86+C86 -> 0
A87: Furniture and Fittings | B87: 0 | C87: -474600 | D87: =B87+C87 -> -474600
A88: Land | B88: 0 | D88: =B88+C88 -> 0
A89: Motor Vehicles | B89: 0 | C89: 531511.91 | D89: =B89+C89 -> 531511.91
A90: s
A91: Net cash used in Investing | B91: =B86+B87+B89+B85 -> -270533000 | C91: =C86+C87+C89+C85+C88 -> -15603088 | D91: =B91+C91 -> -2.8613609e+08
A94: Net Surplus or Deficit | B94: =B82+B91 -> 10741513 | C94: =C82+C91 -> 5306659.4 | D94: =D82+D91 -> 59761484

Sheet April Financial Statement
A1: The Master's Place International Church, Headquaters -Warri
A2: Income & Expenditure Statement
A3: 45777
A5: DESCRIPTION | B5: Balance B/F | C5: April | D5: YEAR TO DATE
A6: Opening Balance | B6: 43713312 | C6: 4774147.8 | D6: =B6+C6 -> 48487460
A7: Income (A)
A8: Home Connect Offering | B8: 362150 | C8: 354410 | D8: =B8+C8 -> 716560
A9: OFFERING | B9: 51931386 | C9: 15344866 | D9: =B9+C9 -> 67276252
A10: PROJECT OFFERING | B10: 119844680 | C10: 166463408 | D10: =B10+C10 -> 286308088
A11: SACRIFICE | B11: 306904158 | C11: 42639956 | D11: =B11+C11 -> 349544114
A12: STUDIO-RESOURCE MATERIAL | B12: 3766976 | C12: 733479 | D12: =B12+C12 -> 4500455
A13: SALES OF MATERIAL OFFERING | B13: 0 | C13: 0 | D13: =B13+C13 -> 0
A14: THANKSGIVING OFFERING | B14: 16885481 | C14: 7963104 | D14: =B14+C14 -> 24848585
A15: TITHE | B15: 49520215 | C15: 19904653 | D15: =B15+C15 -> 69424868
A16: TMA FEE | B16: 0 | C16: 2000 | D16: =B16+C16 -> 2000
A17: TMP BENIN | B17: 904691 | C17: 230500 | D17: =B17+C17 -> 1135191
A18: TMP OGBOMOSO | B18: 1106000 | C18: 823000 | D18: =B18+C18 -> 1929000
A19: TMP SAPELE | B19: 610000 | C19: 343000 | D19: =B19+C19 -> 953000
A20: TMP PORTHARCOURT | C20: 220000
A21: TMP UGHELI | B21: 1878906 | C21: 700000 | D21: =B21+C21 -> 2578906
A22: Total Revenues | B22: =SUM(B6:B21) -> 5.9742795e+08 | C22: =SUM(C6:C21) -> 2.6049652e+08 | D22: =SUM(D6:D21) -> 8.5770448e+08
A24: Other Income (B)
A25: Interest Received from FX | B25: 0 | C25: 0 | D25: =B25+C25 -> 0
A26: TMP Ebrumede | B26: 102000 | C26: 0 | D26: =B26+C26 -> 102000
A27: TMP Orhuwhorun | B27: 0 | C27: 0 | D27: =B27+C27 -> 0
A28: TMP Osubi | B28: 114000 | C28: 149000 | D28: =B28+C28 -> 263000
A29: TMP Otokutu | B29: 175182 | C29: 112256 | D29: =B29+C29 -> 287438
A30: TMP Ubeji | B30: -23871 | C30: 117918 | D30: =B30+C30 -> 94047
A31: TMP Udu | B31: 0 | C31: 80000 | D31: =B31+C31 -> 80000
A32: TMP Ugbuwangue | B32: 318000 | C32: 0 | D32: =B32+C32 -> 318000
A33: TMP Ughoton | B33: 241380 | C33: 112500 | D33: =B33+C33 -> 353880
A34: TMP Warri Central | B34: 0 | C34: 655000 | D34: =B34+C34 -> 655000
A35: TMP Warri G.R.A | B35: 0 | C35: 25000 | D35: =B35+C35 -> 25000
A36: Total for other Income | B36: =SUM(B25:B35) -> 926691 | C36: =SUM(C25:C35) -> 1251674 | D36: =SUM(D25:D35) -> 2178365
A38: TOTAL REVENUE | B38: =B22+B36 -> 5.9835465e+08 | C38: =C22+C36 -> 2.617482e+08 | D38: =D22+D36 -> 8.5988284e+08
A41: Expenditure (C)
A42: Advert & Publicity | B42: 26591210 | C42: 8027430 | D42: =B42+C42 -> 34618640
A43: Allowances and Bonus | B43: 0 | C43: 0 | D43: =B43+C43 -> 0
A44: Bank Charges | B44: 1351485 | C44: 572285 | D44: =B44+C44 -> 1923770
A45: Chairs/Canopies Rent | B45: 9010000 | C45: 3608000 | D45: =B45+C45 -> 12618000
A46: Church Service Expense | B46: 1200000 | C46: 400000 | D46: =B46+C46 -> 1600000
A47: Consumables | B47: 1267060 | C47: 795820 | D47: =B47+C47 -> 2062880
A48: Diesel | B48: 20576000 | C48: 9720000 | D48: =B48+C48 -> 30296000
A49: Electricity | B49: 328000 | C49: 50000 | D49: =B49+C49 -> 378000
A50: Entertainment | B50: 6807000 | C50: 1961000 | D50: =B50+C50 -> 8768000
A51: Forex Expense | B51: 0 | C51: 2000000 | D51: =B51+C51 -> 2000000
A52: Fuel | B52: 8408000 | C52: 3418000 | D52: =B52+C52 -> 11826000
A53: Generator Repairs & Mtce | B53: 2388400 | C53: 725000 | D53: =B53+C53 -> 3113400
... A77: Kingdom Investment | B77: 55000000 | C77: 0 | D77: =B77+C77 -> 55000000
A78: Total Expenses | B78: =SUM(B42:B77) -> 296170385 | C78: =SUM(C42:C77) -> 126378265 | D78: =B78+C78 -> 422548650
A80: Net Income | B80: =(ROUND(B6+B38-B78, 5)) -> 3.4589757e+08 | C80: =C38-C78 -> 1.3536993e+08 | D80: =(ROUND((D6+D38)-D78, 5)) -> 4.8582165e+08
A82: Cash Flow (C)
A83: Building | B83: -286193000 | C83: -130072000 | D83: =B83+C83 -> -416265000
A84: Equipment | B84: 0 | C84: 0 | D84: =B84+C84 -> 0
A85: Furniture and Fittings | B85: -474600 | C85: 0 | D85: =B85+C85 -> -474600
A86: Land | B86: 0 | C86: 0 | D86: =B86+C86 -> 0
A87: Motor Vehicles | B87: 0 | C87: 0 | D87: =B87+C87 -> 0
A89: Net cash used in Investing | B89: =B84+B85+B87+B83 -> -286667600 | C89: =C84+C85+C87+C83+C86 -> -130072000 | D89: =B89+C89 -> -416739600
A92: Net Surplus or Deficit | B92: =B80+B89 -> 59229972 | C92: =C80+C89 -> 5297932.8 | D92: =D80+D89 -> 69082053

Sheet May Financial Statement
A1: The Master's Place International Church, Headquaters -Warri
A2: Income & Expenditure Statement
A3: 45808
A5: DESCRIPTION | B5: Balance B/F | C5: May | D5: YEAR TO DATE
A6: Opening Balance | B6: 48487460 | C6: 5297933 | D6: =B6+C6 -> 53785392
A7: Income (A)
A8: Home Connect Offering | B8: 716560 | C8: 340170 | D8: =B8+C8 -> 1056730
A9: OFFERING | B9: 67276252 | C9: 14883258 | D9: =B9+C9 -> 82159510
A10: PROJECT OFFERING | B10: 286308088 | C10: 38219779 | D10: =B10+C10 -> 324527867
A11: SACRIFICE | B11: 349544114 | C11: 9894400 | D11: =B11+C11 -> 359438514
A12: STUDIO-RESOURCE MATERIAL | B12: 4500455 | C12: 718601 | D12: =B12+C12 -> 5219056
A13: SALES OF MATERIAL OFFERING | B13: 0 | C13: 0 | D13: =B13+C13 -> 0
A14: THANKSGIVING OFFERING | B14: 24848585 | C14: 736500 | D14: =B14+C14 -> 25585085
A15: TITHE | B15: 69424868 | C15: 14404981 | D15: =B15+C15 -> 83829849
A16: TMA FEE | B16: 2000 | C16: 0 | D16: =B16+C16 -> 2000
A17: TMP BENIN | B17: 1135191 | C17: 305106 | D17: =B17+C17 -> 1440297
A18: TMP OGBOMOSO | B18: 1929000 | C18: 606000 | D18: =B18+C18 -> 2535000
A19: TMP SAPELE | B19: 953000 | C19: 56586 | D19: =B19+C19 -> 1009586
... A21: TMP UGHELI | B21: 2076906 | C21: 524000 | D21: =B21+C21 -> 2600906
A22: Total Revenues | B22: =SUM(B6:B21) -> 8.5792448e+08 | C22: =SUM(C6:C21) -> 86319844 | D22: =B22+C22 -> 9.4424432e+08
A24: Other Income (B)
A25: Interest Received from FX | B25: 0 | C25: 0 | D25: =B25+C25 -> 0
A26: TMP Ebrumede | B26: 102000 | C26: 0 | D26: =B26+C26 -> 102000
A27: TMP Orhuwhorun | B27: 0 | C27: 430000 | D27: =B27+C27 -> 430000
A28: TMP Osubi | B28: 263000 | C28: 108000 | D28: =B28+C28 -> 371000
A29: TMP Otokutu | B29: 287438 | C29: 0 | D29: =B29+C29 -> 287438
A30: TMP Ubeji | B30: 94047 | C30: 0 | D30: =B30+C30 -> 94047
A31: TMP Udu | B31: 80000 | C31: 72000 | D31: =B31+C31 -> 152000
A32: TMP Ugbuwangue | B32: 318000 | C32: 146878 | D32: =B32+C32 -> 464878
A33: TMP Ughoton | B33: 353880 | C33: 120000 | D33: =B33+C33 -> 473880
A34: TMP Warri Central | B34: 655000 | C34: 350000 | D34: =B34+C34 -> 1005000
A35: TMP Warri G.R.A | B35: 25000 | C35: 0 | D35: =B35+C35 -> 25000
A36: Total for other Income | B36: =SUM(B25:B35) -> 2178365 | C36: =SUM(C25:C35) -> 1226878 | D36: =SUM(D25:D35) -> 3405243
A38: TOTAL REVENUE | B38: =B22+B36 -> 8.6010284e+08 | C38: =C22+C36 -> 87546722 | D38: =D22+D36 -> 9.4764957e+08
A41: Expenditure (C)
A42: Advert & Publicity | B42: 34618640 | C42: 6992900 | D42: =B42+C42 -> 41611540
A43: Allowances and Bonus | B43: 0 | C43: 900000 | D43: =B43+C43 -> 900000
A44: Bank Charges | B44: 1923770 | C44: 306134 | D44: =B44+C44 -> 2229904
A45: Chairs/Canopies Rent | B45: 12618000 | C45: 300000 | D45: =B45+C45 -> 12918000
A46: Church Service Expense | B46: 1600000 | C46: 450000 | D46: =B46+C46 -> 2050000
A47: Consumables | B47: 2062880 | C47: 712000 | D47: =B47+C47 -> 2774880
A48: Diesel | B48: 30296000 | C48: 7560000 | D48: =B48+C48 -> 37856000
A49: Electricity | B49: 378000 | C49: 100000 | D49: =B49+C49 -> 478000
A50: Entertainment | B50: 8768000 | C50: 669000 | D50: =B50+C50 -> 9437000
A51: Forex Expense | B51: 2000000 | C51: 0 | D51: =B51+C51 -> 2000000
A52: Fuel | B52: 11826000 | C52: 2458000 | D52: =B52+C52 -> 14284000
A53: Generator Repairs & Mtce | B53: 3113400 | C53: 166500 | D53: =B53+C53 -> 3279900
... A77: Kingdom Investment | B77: 55000000 | C77: 10000000 | D77: =B77+C77 -> 65000000
A78: Total Expenses | B78: =ROUND(SUBTOTAL(9, B41:B77), 5) -> 422548650 | C78: =ROUND(SUBTOTAL(9, C41:C77), 5) -> 75342684 | D78: =B78+C78 -> 497891334
A80: Net Income | B80: 4.8605174e+08 | C80: =C38-C78 -> 12204038 | D80: =(ROUND((D6+D38)-D78, 5)) -> 5.0354362e+08
A82: Cash Flow (C)
A83: Building | B83: -416265000 | C83: -3134000 | D83: =B83+C83 -> -419399000
A84: Equipment | B84: 0 | C84: -6196600 | D84: =B84+C84 -> -6196600
A85: Furniture and Fittings | B85: -474600 | D85: -474600
A86: Land | B86: 0 | D86: 0
A87: Motor Vehicles
A88: Zenith Bank (Main) | C88: 55305.81
A89: Zenith Bank Partnership | B89: 5044 | C89: 0 | D89: 5044
A91: Net cash used in Investing | B91: =SUM(B83:B90) -> -416734556 | C91: =SUM(C83:C90) -> -9275294.2 | D91: =SUM(D83:D89) -> -426065156
A94: Net Surplus or Deficit | B94: =B80+B91 -> 69317185 | C94: =C80+C91 -> 2928743.8 | D94: 77013590

Sheet June Financial Statement
A1: The Master's Place International Church, Headquaters -Warri
A2: Income & Expenditure Statement
A3: 45838
A5: DESCRIPTION | B5: Balance B/F | C5: June | D5: YEAR TO DATE
A6: Opening Balance | B6: 53790436 | C6: 2928743.4 | D6: 56719180
A7: Income (A)
A8: Home Connect Offering | B8: 1056730 | C8: 0 | D8: =B8+C8 -> 1056730
A9: OFFERING | B9: 82159510 | C9: 18114551 | D9: =B9+C9 -> 100274061
A10: PROJECT OFFERING | B10: 324527867 | C10: 47490621 | D10: =B10+C10 -> 372018488
A11: SACRIFICE | B11: 359438514 | C11: 19470245 | D11: =B11+C11 -> 378908759
A12: STUDIO-RESOURCE MATERIAL | B12: 5219056 | C12: 0 | D12: =B12+C12 -> 5219056
A13: SALES OF MATERIAL OFFERING | B13: 0 | C13: 0 | D13: =B13+C13 -> 0
A14: THANKSGIVING OFFERING | B14: 25585085 | C14: 1179820 | D14: =B14+C14 -> 26764905
A15: TITHE | B15: 83829849 | C15: 13889670 | D15: =B15+C15 -> 97719519
A16: TMA FEE | B16: 2000 | C16: 0 | D16: =B16+C16 -> 2000
A17: TMP BENIN | B17: 1440297 | C17: 247742 | D17: =B17+C17 -> 1688039
A18: TMP OGBOMOSO | B18: 2535000 | C18: 680000 | D18: =B18+C18 -> 3215000
A19: TMP SAPELE | B19: 1009586 | C19: 138000 | D19: =B19+C19 -> 1147586
... A21: TMP UGHELI | B21: 2600906 | C21: 685260 | D21: =B21+C21 -> 3286166
A22: Total Revenues | B22: =SUM(B6:B21) -> 9.4424937e+08 | C22: =SUM(C6:C21) -> 1.0513186e+08 | D22: =SUM(D6:D21) -> 1.0493812e+09
A24: Other Income (B)
A25: Interest Received from FX | B25: 0 | C25: 0 | D25: =B25+C25 -> 0
A26: TMP Ebrumede | B26: 102000 | C26: 0 | D26: =B26+C26 -> 102000
A27: TMP Orhuwhorun | B27: 430000 | C27: 0 | D27: =B27+C27 -> 430000
A28: TMP Osubi | B28: 371000 | C28: 88000 | D28: =B28+C28 -> 459000
A29: TMP Otokutu | B29: 287438 | C29: 90210 | D29: =B29+C29 -> 377648
A30: TMP Ubeji | B30: 94047 | C30: 0 | D30: =B30+C30 -> 94047
A31: TMP Udu | B31: 152000 | C31: 36000 | D31: =B31+C31 -> 188000
A32: TMP Ugbuwangue | B32: 464878 | C32: 0 | D32: =B32+C32 -> 464878
A33: TMP Ughoton | B33: 473880 | C33: 86000 | D33: =B33+C33 -> 559880
A34: TMP Warri Central | B34: 1005000 | C34: 370000 | D34: =B34+C34 -> 1375000
A35: TMP Warri G.R.A | B35: 25000 | C35: 0 | D35: =B35+C35 -> 25000
A36: Total for other Income | B36: =SUM(B25:B35) -> 3405243 | C36: =SUM(C25:C35) -> 670210 | D36: =SUM(D25:D35) -> 4075453
A38: TOTAL REVENUE | B38: =B22+B36 -> 9.4765461e+08 | C38: =C22+C36 -> 1.0580207e+08 | D38: =D22+D36 -> 1.0534567e+09
A41: Expenditure (C)
A42: Advert & Publicity | B42: 41611540 | C42: 9540106 | D42: =B42+C42 -> 51151646
A43: Allowances and Bonus | B43: 900000 | C43: 1730000 | D43: =B43+C43 -> 2630000
A44: Bank Charges | B44: 2229904 | C44: 263771 | D44: =B44+C44 -> 2493675
A45: Chairs/Canopies Rent | B45: 12918000 | C45: 2090000 | D45: =B45+C45 -> 15008000
A46: Church Service Expense | B46: 2050000 | C46: 354000 | D46: =B46+C46 -> 2404000
A47: Consumables | B47: 2774880 | C47: 426160 | D47: =B47+C47 -> 3201040
A48: Diesel | B48: 37856000 | C48: 6570000 | D48: =B48+C48 -> 44426000
A49: Electricity | B49: 478000 | C49: 50000 | D49: =B49+C49 -> 528000
A50: Entertainment | B50: 9437000 | C50: 1255200 | D50: =B50+C50 -> 10692200
A51: Forex Expense | B51: 2000000 | C51: 0 | D51: =B51+C51 -> 2000000
A52: Fuel | B52: 14284000 | C52: 1785000 | D52: =B52+C52 -> 16069000
A53: Generator Repairs & Mtce | B53: 3279900 | C53: -521500 | D53: =B53+C53 -> 2758400
... A77: Kingdom Investment | B77: 65000000 | C77: 0 | D77: =B77+C77 -> 65000000
A78: Total Expenses | B78: =ROUND(SUBTOTAL(9, B41:B77), 5) -> 497891334 | C78: =ROUND(SUBTOTAL(9, C41:C77), 5) -> 90927037 | D78: =B78+C78 -> 588818371
A80: Net Income | B80: =(ROUND(B6+B38-B78, 5)) -> 5.0355371e+08 | C80: =C38-C78 -> 14875031 | D80: 5.2135749e+08
A82: Cash Flow (C)
A83: Building | B83: -419399000 | C83: -10062500 | D83: =B83+C83 -> -429461500
A84: Equipment | B84: -6196600 | C84: 0 | D84: =B84+C84 -> -6196600
A85: Furniture and Fittings | B85: -474600 | D85: =B85+C85 -> -474600
A86: Land | B86: 0 | D86: =B86+C86 -> 0
A87: Motor Vehicles
A88: GTB | C88: 55802.64 | D88: =C88 -> 55802.64
A89: Zenith Bank (Main) | C89: -55305 | D89: =C89 -> -55305
A90: Zenith Bank Partnership | B90: 5044 | C90: 68422.9 | D90: =B90+C90 -> 73466.9
A92: Net cash used in Investing | B92: =B84+B85+B90+B83+B86 -> -426065156 | C92: =C84+C85+C90+C83+C86+C88+C89 -> -9993579.5 | D92: =SUM(D83:D90) -> -4.3605874e+08
A95: Net Surplus or Deficit | B95: 77013590 | C95: =C80+C92 -> 4881451.9 | D95: =D80+D92 -> 85298751

Sheet July Financial Statement
A1: The Master's Place International Church, Headquaters -Warri
A2: Income & Expenditure Statement
A3: 45869
A5: DESCRIPTION | B5: Balance B/F | C5: July | D5: YEAR TO DATE
A6: Opening Balance | B6: 56719180 | C6: 4757226.9 | D6: =B6+C6 -> 61476407
A7: Income (A)
A8: Home Connect Offering | B8: 1056730 | C8: 343310 | D8: =B8+C8 -> 1400040
A9: OFFERING | B9: 100274061 | C9: 31564548 | D9: =B9+C9 -> 131838609
A10: PROJECT OFFERING | B10: 372018488 | C10: 172134500 | D10: =B10+C10 -> 544152988
A11: SACRIFICE | B11: 378908759 | C11: 61766568 | D11: =B11+C11 -> 440675327
A12: STUDIO-RESOURCE MATERIAL | B12: 5219056 | C12: 6499411 | D12: =B12+C12 -> 11718467
A13: SALES OF MATERIAL OFFERING | B13: 0 | C13: 0 | D13: =B13+C13 -> 0
A14: THANKSGIVING OFFERING | B14: 26764905 | C14: 1043199 | D14: =B14+C14 -> 27808104
A15: TITHE | B15: 97719519 | C15: 27035344 | D15: =B15+C15 -> 124754863
A16: TMA FEE | B16: 2000 | C16: 0 | D16: =B16+C16 -> 2000
A17: TMP BENIN | B17: 1688039 | C17: 217830 | D17: =B17+C17 -> 1905869
A18: TMP OGBOMOSO | B18: 3215000 | C18: 592000 | D18: =B18+C18 -> 3807000
A19: TMP SAPELE | B19: 1147586 | C19: 150490 | D19: =B19+C19 -> 1298076
... A21: TMP UGHELI | B21: 3286166 | C21: 3410000 | D21: =B21+C21 -> 6696166
A22: Total Revenues | B22: =SUM(B6:B21) -> 1.0493812e+09 | C22: =SUM(C6:C21) -> 3.0993043e+08 | D22: =B22+C22 -> 1.3593117e+09
A24: Other Income (B)
A25: Interest Received from FX | B25: 0 | C25: 0 | D25: =B25+C25 -> 0
A26: TMP Ebrumede | B26: 102000 | C26: 0 | D26: =B26+C26 -> 102000
A27: TMP Orhuwhorun | B27: 430000 | C27: 0 | D27: =B27+C27 -> 430000
A28: TMP Osubi | B28: 459000 | C28: 168000 | D28: =B28+C28 -> 627000
A29: TMP Otokutu | B29: 377648 | C29: 108244 | D29: =B29+C29 -> 485892
A30: TMP Ubeji | B30: 94047 | C30: 0 | D30: =B30+C30 -> 94047
A31: TMP Udu | B31: 188000 | C31: 0 | D31: =B31+C31 -> 188000
A32: TMP Ugbuwangue | B32: 464878 | C32: 0 | D32: =B32+C32 -> 464878
A33: TMP Ughoton | B33: 559880 | C33: 0 | D33: =B33+C33 -> 559880
A34: TMP Warri Central | B34: 1375000 | C34: 350000 | D34: =B34+C34 -> 1725000
A35: TMP Warri G.R.A | B35: 25000 | C35: 0 | D35: =B35+C35 -> 25000
A36: Total for other Income | B36: =VLOOKUP(A36,'June Financial Statement'!A36:D123,4,0) -> 4075453 | C36: =SUM(C25:C35) -> 626244 | D36: =SUM(D25:D35) -> 4701697
A38: TOTAL REVENUE | B38: =VLOOKUP(A38,'June Financial Statement'!A38:D125,4,0) -> 1.0534567e+09 | C38: =C22+C36 -> 3.1055667e+08 | D38: =D22+D36 -> 1.3640133e+09
A41: Expenditure (C)
A42: Advert & Publicity | B42: 51151646 | C42: 5046786 | D42: =B42+C42 -> 56198432
A43: Allowances and Bonus | B43: 2630000 | C43: 1380000 | D43: =B43+C43 -> 4010000
A44: Bank Charges | B44: 2493675 | C44: 813050 | D44: =B44+C44 -> 3306725
A45: Chairs/Canopies Rent | B45: 15008000 | C45: 8735000 | D45: =B45+C45 -> 23743000
A46: Church Service Expense | B46: 2404000 | C46: 492000 | D46: =B46+C46 -> 2896000
A47: Consumables | B47: 3201040 | C47: 0 | D47: =B47+C47 -> 3201040
A48: Diesel | B48: 44426000 | C48: 9720000 | D48: =B48+C48 -> 54146000
A49: Electricity | B49: 528000 | C49: 100000 | D49: =B49+C49 -> 628000
A50: Entertainment | B50: 10692200 | C50: 1187700 | D50: =B50+C50 -> 11879900
A51: Forex Expense | B51: 2000000 | C51: 0 | D51: =B51+C51 -> 2000000
A52: Fuel | B52: 16069000 | C52: 2131000 | D52: =B52+C52 -> 18200000
A53: Generator Repairs & Mtce | B53: 2758400 | C53: 511800 | D53: =B53+C53 -> 3270200
... A67: Repair & Maintenance -Resident | B67: 4799650 | C67: 12031300 | D67: =B67+C67 -> 16830950
A68: Repair & Maintenance - Office | B68: 0 | C68: 0 | D68: 0
A69: Resource Center | B69: 1125000 | C69: 10367000 | D69: =B69+C69 -> 11492000
A70: Salaries | B70: 32880675 | C70: 6820480 | D70: =B70+C70 -> 39701155
A71: Security | B71: 8948500 | C71: 6945000 | D71: =B71+C71 -> 15893500
A72: Studio | B72: 0 | C72: 0 | D72: =B72+C72 -> 0
A73: Telephone & Internet | B73: 1780000 | C73: 10727634 | D73: =B73+C73 -> 12507634
A74: Transport & Travelling | B74: 144196510 | C74: 43535500 | D74: =B74+C74 -> 187732010
A75: Vehicle Maintenance | B75: 1878400 | C75: 303500 | D75: =B75+C75 -> 2181900
A76: Video Coverage | B76: 10674600 | C76: 2415350 | D76: =B76+C76 -> 13089950
A77: Welfare | B77: 7712900 | C77: 3421800 | D77: =B77+C77 -> 11134700
A78: Kingdom Investment | B78: 65000000 | C78: 53240000 | D78: =B78+C78 -> 118240000
A79: Total Expenses | B79: =SUM(B42:B78) -> 588818371 | C79: =ROUND(SUBTOTAL(9, C41:C78), 5) -> 212925000 | D79: =SUM(D42:D78) -> 801743371
A81: Net Income | B81: 5.2135749e+08 | C81: =C38-C79 -> 97631671 | D81: =(ROUND((D6+D38)-D79, 5)) -> 6.2374638e+08
A83: Cash Flow (C)
A84: Building | B84: -429461500 | C84: -85552500 | D84: =B84+C84 -> -515014000
A85: Equipment | B85: -6196600 | D85: =B85+C85 -> -6196600
A86: Furniture and Fittings | B86: -474600 | C86: -2730000 | D86: =B86+C86 -> -3204600
A87: Land | B87: 0 | D87: =B87+C87 -> 0
A88: Motor Vehicles
A89: GTB | B89: 55802.64 | D89: =B89 -> 55802.64
A90: Zenith Bank (Main) | B90: -55305 | D90: =B90 -> -55305
A91: Zenith Bank Partnership | B91: 73466.9 | C91: 33867.71 | D91: =B91+C91 -> 107334.61
A93: Net cash used in Investing | B93: -4.3605874e+08 | C93: =C85+C86+C91+C84+C87+C88+C90+C89 -> -88248632 | D93: =B93+C93 -> -5.2430737e+08
A96: Net Surplus or Deficit | B96: 85298751 | C96: =C81+C93 -> 9383038.6 | D96: 98973641

Sheet August Financial Statement
A1: The Master's Place International Church, Headquaters -Warri
A2: Income & Expenditure Statement
A3: 45900
A5: DESCRIPTION | B5: Balance B/F | C5: August | D5: YEAR TO DATE
A6: Opening Balance | B6: 61476407 | C6: 9349171 | D6: =B6+C6 -> 70825578
A7: Income (A)
A8: Home Connect Offering | B8: 1400040 | C8: 0 | D8: =B8+C8 -> 1400040
A9: OFFERING | B9: 131838609 | C9: 19925622 | D9: =B9+C9 -> 151764231
A10: PROJECT OFFERING | B10: 544152988 | C10: 53238738 | D10: =B10+C10 -> 597391726
A11: SACRIFICE | B11: 440675327 | C11: 110410500 | D11: =B11+C11 -> 551085827
A12: STUDIO-RESOURCE MATERIAL | B12: 11718467 | C12: 1551635 | D12: =B12+C12 -> 13270102
A13: SALES OF MATERIAL OFFERING | B13: 0 | C13: 0 | D13: =B13+C13 -> 0
A14: THANKSGIVING OFFERING | B14: 27808104 | C14: 4038502 | D14: =B14+C14 -> 31846606
A15: TITHE | B15: 124754863 | C15: 17119300 | D15: =B15+C15 -> 141874163
A16: TMA FEE | B16: 2000 | C16: 0 | D16: =B16+C16 -> 2000
A17: TMP BENIN | B17: 1905869 | C17: 189600 | D17: =B17+C17 -> 2095469
A18: TMP OGBOMOSO | B18: 3807000 | C18: 0 | D18: =B18+C18 -> 3807000
A19: TMP SAPELE | B19: 1298076 | C19: 0 | D19: =B19+C19 -> 1298076
... A21: TMP UGHELI | B21: 6696166 | C21: 0 | D21: =B21+C21 -> 6696166
A22: Total Revenues | B22: =SUM(B6:B21) -> 1.3593117e+09 | C22: =SUM(C6:C21) -> 2.1582307e+08 | D22: =B22+C22 -> 1.5751347e+09
A24: Other Income (B)
A25: Interest Received from FX | B25: 0 | C25: 0 | D25: =B25+C25 -> 0
A26: TMP Ebrumede | B26: 102000 | C26: 0 | D26: =B26+C26 -> 102000
A27: TMP Orhuwhorun | B27: 430000 | C27: 0 | D27: =B27+C27 -> 430000
A28: TMP Osubi | B28: 627000 | C28: 108000 | D28: =B28+C28 -> 735000
A29: TMP Otokutu | B29: 485892 | C29: 0 | D29: =B29+C29 -> 485892
A30: TMP Ubeji | B30: 94047 | C30: 0 | D30: =B30+C30 -> 94047
A31: TMP Udu | B31: 188000 | C31: 0 | D31: =B31+C31 -> 188000
A32: TMP Ugbuwangue | B32: 464878 | C32: 0 | D32: =B32+C32 -> 464878
A33: TMP Ughoton | B33: 559880 | C33: 0 | D33: =B33+C33 -> 559880
A34: TMP Warri Central | B34: 1725000 | C34: 220000 | D34: =B34+C34 -> 1945000
A35: TMP Warri G.R.A | B35: 25000 | C35: 0 | D35: =B35+C35 -> 25000
A36: Total for other Income | B36: =SUM(B25:B35) -> 4701697 | C36: =SUM(C25:C35) -> 328000 | D36: =SUM(D25:D35) -> 5029697
A38: TOTAL REVENUE | B38: =B22+B36 -> 1.3640133e+09 | C38: =C22+C36 -> 2.1615107e+08 | D38: =D22+D36 -> 1.5801644e+09
A41: Expenditure (C)
A42: Advert & Publicity | B42: 56198432 | C42: 10365910 | D42: =B42+C42 -> 66564342
A43: Allowances and Bonus | B43: 4010000 | C43: 650000 | D43: =B43+C43 -> 4660000
A44: Bank Charges | B44: 3306725 | C44: 427870 | D44: =B44+C44 -> 3734595
A45: Chairs/Canopies Rent | B45: 23743000 | C45: 4070000 | D45: =B45+C45 -> 27813000
A46: Church Service Expense | B46: 2896000 | C46: 490000 | D46: =B46+C46 -> 3386000
A47: Consumables | B47: 3201040 | C47: 218860 | D47: =B47+C47 -> 3419900
A48: Diesel | B48: 54146000 | C48: 9140000 | D48: =B48+C48 -> 63286000
A49: Electricity | B49: 628000 | C49: 100000 | D49: =B49+C49 -> 728000
A50: Entertainment | B50: 11879900 | C50: 413000 | D50: =B50+C50 -> 12292900
A51: Forex Expense | B51: 2000000 | C51: 0 | D51: =B51+C51 -> 2000000
A52: Fuel | B52: 18200000 | C52: 3055000 | D52: =B52+C52 -> 21255000
A53: Generator Repairs & Mtce | B53: 3270200 | C53: 0 | D53: =B53+C53 -> 3270200
... A77: Kingdom Investment | B77: 118240000 | C77: 20000000 | D77: =B77+C77 -> 138240000
A78: Total Expenses | B78: =SUM(B42:B77) -> 801743371 | C78: =SUM(C42:C77) -> 113296592 | D78: =B78+C78 -> 915039963
A80: Net Income | B80: =(ROUND(B6+B38-B78, 5)) -> 6.2374638e+08 | C80: =C38-C78 -> 1.0285448e+08 | D80: =(ROUND((D6+D38)-D78, 5)) -> 7.3595003e+08
A82: Cash Flow (C)
A83: Building | B83: -515014000 | C83: -93052000 | D83: =B83+C83 -> -608066000
A84: Equipment | B84: -6196600 | D84: =B84+C84 -> -6196600
A85: Furniture and Fittings | B85: -3204600 | C85: -2900000 | D85: =B85+C85 -> -6104600
A86: Land | B86: 0 | D86: =B86+C86 -> 0
A87: Current Liabilities | D87: =B87+C87 -> 0
A88: GTB | B88: 55802.64 | C88: 10734.8 | D88: =B88+C88 -> 66537.44
A89: Zenith Bank (Main) | B89: -55305 | D89: =B89+C89 -> -55305
A90: Zenith Bank Partnership | B90: 107334.61 | C90: 20064.4 | D90: =B90+C90 -> 127399.01
A92: Net cash used in Investing | B92: =B83+B85+B86+B91+B84+B90 -> -5.2430787e+08 | C92: =C83+C85+C86+C91+C84+C87+C88+C90+C89 -> -95921201 | D92: =B92+C92 -> -6.2022907e+08
A95: Net Surplus or Deficit | B95: =B80+B92 -> 99438519 | C95: =C80+C92 -> 6933275.2 | D95: =D80+D92 -> 1.1572097e+08

Sheet September Financial Statement
A1: The Master's Place International Church, Headquaters -Warri
A2: Income & Expenditure Statement
A3: 45930
A5: DESCRIPTION | B5: Balance B/F | C5: September | D5: YEAR TO DATE
A6: Opening Balance | B6: 70825578 | C6: 6902476 | D6: =B6+C6 -> 77728054
A7: Income (A)
A8: Home Connect Offering | B8: 1400040 | C8: 293770 | D8: =B8+C8 -> 1693810
A9: OFFERING | B9: 151764231 | C9: 17200306 | D9: =B9+C9 -> 168964537
A10: PROJECT OFFERING | B10: 597391726 | C10: 221034851 | D10: =B10+C10 -> 818426577
A11: SACRIFICE | B11: 551085827 | C11: 93834040 | D11: =B11+C11 -> 644919867
A12: STUDIO-RESOURCE MATERIAL | B12: 13270102 | C12: 1697973 | D12: =B12+C12 -> 14968075
A13: SALES OF MATERIAL OFFERING | B13: 0 | C13: 0 | D13: =B13+C13 -> 0
A14: THANKSGIVING OFFERING | B14: 31846606 | C14: 3190775 | D14: =B14+C14 -> 35037381
A15: TITHE | B15: 141874163 | C15: 16420873 | D15: =B15+C15 -> 158295036
A16: TMA FEE | B16: 2000 | C16: 0 | D16: =B16+C16 -> 2000
A17: TMP BENIN | B17: 2095469 | C17: 165968 | D17: =B17+C17 -> 2261437
A18: TMP OGBOMOSO | B18: 3807000 | C18: 501000 | D18: =B18+C18 -> 4308000
A19: TMP SAPELE | B19: 1298076 | C19: 103000 | D19: =B19+C19 -> 1401076
A20: TMP PORTHARCOURT | B20: 1777736 | C20: 0
A21: TMP UGHELLI | B21: 6696166 | C21: 383600 | D21: =B21+C21 -> 7079766
A22: Total Revenues | B22: =SUM(B6:B21) -> 1.5751347e+09 | C22: =SUM(C6:C21) -> 3.6172863e+08 | D22: =B22+C22 -> 1.9368634e+09
A24: Other Income (B)
A25: Interest Received from FX | B25: 0 | C25: 0 | D25: =B25+C25 -> 0
A26: TMP Ebrumede | B26: 102000 | C26: 0 | D26: =B26+C26 -> 102000
A27: TMP Orhuwhorun | B27: 430000 | C27: 0 | D27: =B27+C27 -> 430000
A28: TMP Osubi | B28: 735000 | C28: 79000 | D28: =B28+C28 -> 814000
A29: TMP Otokutu | B29: 485892 | C29: 113519 | D29: =B29+C29 -> 599411
A30: TMP Ubeji | B30: 94047 | C30: 0 | D30: =B30+C30 -> 94047
A31: TMP Udu | B31: 188000 | C31: 156000 | D31: =B31+C31 -> 344000
A32: TMP Ugbuwangue | B32: 464878 | C32: 0 | D32: =B32+C32 -> 464878
A33: TMP Ughoton | B33: 559880 | C33: 0 | D33: =B33+C33 -> 559880
A34: TMP Warri Central | B34: 1945000 | C34: 210000 | D34: =B34+C34 -> 2155000
A35: TMP Warri G.R.A | B35: 25000 | C35: 17000 | D35: =B35+C35 -> 42000
A36: Total for other Income | B36: =SUM(B25:B35) -> 5029697 | C36: =SUM(C25:C35) -> 575519 | D36: =SUM(D25:D35) -> 5605216
A38: TOTAL REVENUE | B38: =B22+B36 -> 1.5801644e+09 | C38: =C22+C36 -> 3.6230415e+08 | D38: =D22+D36 -> 1.9424686e+09
A41: Expenditure (C)
A42: Advert & Publicity | B42: 66564342 | C42: 15005340 | D42: =B42+C42 -> 81569682
A43: Allowances and Bonus | B43: 4660000 | C43: 1370000 | D43: =B43+C43 -> 6030000
A44: Bank Charges | B44: 3734595 | C44: 622063 | D44: =B44+C44 -> 4356658
A45: Chairs/Canopies Rent | B45: 27813000 | C45: 0 | D45: =B45+C45 -> 27813000
A46: Church Service Expense | B46: 3386000 | C46: 430000 | D46: =B46+C46 -> 3816000
A47: Consumables | B47: 3419900 | C47: 554720 | D47: =B47+C47 -> 3974620
A48: Diesel | B48: 63286000 | C48: 4900000 | D48: =B48+C48 -> 68186000
A49: Electricity | B49: 728000 | C49: 260000 | D49: =B49+C49 -> 988000
A50: Entertainment | B50: 12292900 | C50: 1101000 | D50: =B50+C50 -> 13393900
A51: Forex Expense | B51: 2000000 | C51: 0 | D51: =B51+C51 -> 2000000
A52: Fuel | B52: 21255000 | C52: 2338000 | D52: =B52+C52 -> 23593000
A53: Generator Repairs & Mtce | B53: 3270200 | C53: 0 | D53: =B53+C53 -> 3270200
A54: Honourarium | B54: 5000000 | C54: 90200000 | D54: =B54+C54 -> 95200000
A55: Hotel Accomodation | B55: 25066000 | C55: 1500000 | D55: =B55+C54 -> 115266000
A56: Instrument/Equipment Rent | B56: 18552850 | C56: 177375 | D56: =B56+C56 -> 18730225
A57: Life Coach | B57: 55309350 | C57: 56813800 | D57: =B57+C57 -> 112123150
A58: Master's tv | B58: 2101050 | C58: 0 | D58: =B58+C58 -> 2101050
A59: Medical Bill | B59: 0 | C59: 0 | D59: =B59+C59 -> 0
A60: Ordinance | B60: 3211300 | C60: 30000 | D60: =B60+C60 -> 3241300
A61: Printing & Stationery | B61: 1505000 | C61: 0 | D61: =B61+C61 -> 1505000
A62: Professional Fees | B62: 16311900 | C62: 0 | D62: =B62+C62 -> 16311900
A63: Rent - Hall | B63: 5806808 | C63: 0 | D63: =B63+C63 -> 5806808
A64: Rent - Official Residence | B64: 34697000 | C64: 840000 | D64: =B64+C64 -> 35537000
A65: Repair & Maint. - Equipment | B65: 11660000 | C65: 0 | D65: =B65+C65 -> 11660000
A66: Repair & Maintenance - Church | B66: 41045880 | C66: 5127800 | D66: =B66+C66 -> 46173680
A67: Repair & Maintenance -Resident | B67: 18061850 | C67: 0 | D67: =B67+C67 -> 18061850
... A77: Kingdom Investment | B77: 138240000 | C77: 5000000 | D77: =B77+C77 -> 143240000
A78: Total Expenses | B78: =SUM(B42:B77) -> 915039963 | C78: =SUM(C42:C77) -> 256723298 | D78: =SUM(B78:C78) -> 1171763261
A80: Net Income | B80: =(ROUND(B6+B38-B78, 5)) -> 7.3595003e+08 | C80: =C38-C78 -> 1.0558085e+08 | D80: =(ROUND((D6+D38)-D78, 5)) -> 8.4843336e+08
A82: Cash Flow (C)
A83: Building | B83: -608066000 | C83: -101940000 | D83: =B83+C83 -> -710006000
A84: Equipment | B84: -6196600 | D84: =B84+C84 -> -6196600
A85: Furniture and Fittings | B85: -6104600 | D85: =B85+C85 -> -6104600
A86: Land | B86: 0 | D86: =B86+C86 -> 0
A87: Motor Vehicles | B87: 0 | D87: =B87+C87 -> 0
A88: GTB | B88: 66537.44
A89: Zenith Bank (Main) | B89: -55305
A90: Zenith Bank Partnership | B90: 127399.01
A91: Access Bank | C91: 868.88 | D91: =B91+C91 -> 868.88
A92: GTB Domiciliary | C92: 10734.8 | D92: =B92+C92 -> 10734.8
A93: Zenith Bank Remittance | C93: 2422.85 | D93: =B93+C93 -> 2422.85
A94: Net cash used in Investing | B94: -6.2022907e+08 | C94: =C84+C85+C87+C83+C91+C92+C93 -> -1.0192597e+08 | D94: =SUM(D83:D93) -> -7.2229317e+08
A97: Net Surplus or Deficit | B97: =B80+B94 -> 1.1572097e+08 | C97: =C80+C94 -> 3654879.5 | D97: =D80+D94 -> 1.2614019e+08

Sheet October Financial Statement
A1: The Master's Place International Church, Headquaters -Warri
A2: Income & Expenditure Statement
A3: 45961
A5: DESCRIPTION | B5: Balance B/F | C5: October | D5: YEAR TO DATE
A6: Opening Balance | B6: 77728054 | C6: 3640852.4 | D6: =B6+C6 -> 81368906
A7: Income (A)
A8: Home Connect Offering | B8: 1693810 | C8: 379130 | D8: =B8+C8 -> 2072940
A9: OFFERING | B9: 168964537 | C9: 16114207 | D9: =B9+C9 -> 185078744
A10: PROJECT OFFERING | B10: 818426577 | C10: 169852187 | D10: =B10+C10 -> 988278764
A11: SACRIFICE | B11: 644919867 | C11: 10412342 | D11: =B11+C11 -> 655332209
A12: STUDIO-RESOURCE MATERIAL | B12: 14968075 | C12: 721783 | D12: =B12+C12 -> 15689858
A13: SALES OF MATERIAL OFFERING | B13: 0 | C13: 0 | D13: =B13+C13 -> 0
A14: THANKSGIVING OFFERING | B14: 35037381 | C14: 981400 | D14: =B14+C14 -> 36018781
A15: TITHE | B15: 158295036 | C15: 15114697 | D15: =B15+C15 -> 173409733
A16: TMA FEE | B16: 2000 | C16: 0 | D16: =B16+C16 -> 2000
A17: TMP BENIN | B17: 2261437 | C17: 315773 | D17: =B17+C17 -> 2577210
A18: TMP OGBOMOSO | B18: 4308000 | C18: 551000 | D18: =B18+C18 -> 4859000
A19: TMP SAPELE | B19: 1401076 | C19: 0 | D19: =B19+C19 -> 1401076
... A21: TMP UGHELI | B21: 7079766 | C21: 1043108 | D21: =B21+C21 -> 8122874
A22: Total Revenues | B22: =SUM(B6:B21) -> 1.9368634e+09 | C22: =SUM(C6:C21) -> 2.1912648e+08 | D22: =SUM(D6:D21) -> 2.1559898e+09
A24: Other Income (B)
A25: Interest Received from FX | B25: 0 | C25: 0 | D25: =B25+C25 -> 0
A26: TMP Ebrumede | B26: 102000 | C26: 53200 | D26: =B26+C26 -> 155200
A27: TMP Orhuwhorun | B27: 430000 | C27: 0 | D27: =B27+C27 -> 430000
A28: TMP Osubi | B28: 814000 | C28: 69000 | D28: =B28+C28 -> 883000
A29: TMP Otokutu | B29: 599411 | C29: 48206 | D29: =B29+C29 -> 647617
A30: TMP Ubeji | B30: 94047 | C30: 0 | D30: =B30+C30 -> 94047
A31: TMP Udu | B31: 344000 | C31: 131300 | D31: =B31+C31 -> 475300
A32: TMP Ugbuwangue | B32: 464878 | C32: 0 | D32: =B32+C32 -> 464878
A33: TMP Ughoton | B33: 559880 | C33: 0 | D33: =B33+C33 -> 559880
A34: TMP Warri Central | B34: 2155000 | C34: 170000 | D34: =B34+C34 -> 2325000
A35: TMP Warri G.R.A | B35: 42000 | C35: 0 | D35: =B35+C35 -> 42000
A36: Total for other Income | B36: =SUM(B25:B35) -> 5605216 | C36: =SUM(C25:C35) -> 471706 | D36: =SUM(D25:D35) -> 6076922
A38: TOTAL REVENUE | B38: =B22+B36 -> 1.9424686e+09 | C38: =C22+C36 -> 2.1959819e+08 | D38: =D22+D36 -> 2.1620668e+09
A41: Expenditure (C)
A42: Advert & Publicity | B42: 81569682 | C42: 5344050 | D42: =B42+C42 -> 86913732
A43: Allowances and Bonus | B43: 6030000 | C43: 960000 | D43: =B43+C43 -> 6990000
A44: Bank Charges | B44: 4356658 | C44: 426060 | D44: =B44+C44 -> 4782718
A45: Chairs/Canopies Rent | B45: 27813000 | C45: 0 | D45: =B45+C45 -> 27813000
A46: Church Service Expense | B46: 3816000 | C46: 405000 | D46: =B46+C46 -> 4221000
A47: Consumables | B47: 3974620 | C47: 0 | D47: =B47+C47 -> 3974620
A48: Diesel | B48: 68186000 | C48: 9220000 | D48: =B48+C48 -> 77406000
A49: Electricity | B49: 988000 | C49: 0 | D49: =B49+C49 -> 988000
A50: Entertainment | B50: 13393900 | C50: 245000 | D50: =B50+C50 -> 13638900
A51: Forex Expense | B51: 2000000 | C51: 1788000 | D51: =B51+C51 -> 3788000
A52: Fuel | B52: 23593000 | C52: 2484000 | D52: =B52+C52 -> 26077000
A53: Generator Repairs & Mtce | B53: 3270200 | C53: 85000 | D53: =B53+C53 -> 3355200
... A78: Kingdom Investment | B78: 143240000 | C78: 55465000 | D78: =B78+C78 -> 198705000
A79: Total Expenses | B79: =ROUND(SUBTOTAL(9, B41:B78), 5) -> 1171763261 | C79: =ROUND(SUBTOTAL(9, C41:C78), 5) -> 133158516 | D79: =B79+C79 -> 1304921777
A81: Net Income | B81: =(ROUND(B6+B38-B79, 5)) -> 8.4843336e+08 | C81: =C38-C79 -> 86439669 | D81: =(ROUND((D6+D38)-D79, 5)) -> 9.3851388e+08
A83: Cash Flow (C)
A84: Building | B84: -710006000 | C84: -82500000 | D84: =B84+C84 -> -792506000
A85: Equipment | B85: -6196600 | D85: =B85+C85 -> -6196600
A86: Furniture and Fittings | B86: -6104600 | D86: =B86+C86 -> -6104600
A87: Land | B87: =VLOOKUP(A87,'September Financial Statement'!A85:D175,4,0) -> 0 | D87: =B87+C87 -> 0
A88: Motor Vehicles | D88: =B88+C88 -> 0
A89: Access Bank | B89: 868.88 | D89: =B89+C89 -> 868.88
A90: GTB Domiciliary | B90: 10734.8 | C90: 10734.8 | D90: =B90+C90 -> 21469.6
A91: Zenith Bank Remittance | B91: 2422.85 | C91: 1817.35 | D91: =B91+C91 -> 4240.2
A93: Net cash used in Investing | B93: =B84+B85+B87+B86+B89+B90+B91 -> -7.2229317e+08 | C93: =C85+C86+C91+C84+C90 -> -82487448 | D93: =SUM(D84:D91) -> -8.0478062e+08
A96: Net Surplus or Deficit | B96: =B81+B93 -> 1.2614019e+08 | C96: =C81+C93 -> 3952221.5 | D96: =D81+D93 -> 1.3373326e+08

Sheet November Financial Statement
A1: The Master's Place International Church, Headquaters -Warri
A2: Income & Expenditure Statement
A3: 45991
A5: DESCRIPTION | B5: Balance B/F | C5: November | D5: YEAR TO DATE
A6: Opening Balance | B6: 81368906 | C6: 3939670 | D6: =B6+C6 -> 85308576
A7: Income (A)
A8: Home Connect Offering | B8: 2072940 | C8: 371430 | D8: 2444370
A9: OFFERING | B9: 185078744 | C9: 16806275 | D9: 201885019
A10: PROJECT OFFERING | B10: 988278764 | C10: 49827146 | D10: 1038105910
A11: SACRIFICE | B11: 655332209 | C11: 12416780 | D11: 667748989
A12: STUDIO-RESOURCE MATERIAL | B12: 15689858 | C12: 528521 | D12: 16218379
A13: SALES OF MATERIAL OFFERING | B13: 0 | C13: 0 | D13: 0
A14: THANKSGIVING OFFERING | B14: 36018781 | C14: 3100275 | D14: 39119056
A15: TITHE | B15: 173409733 | C15: 14144976 | D15: 187554709
A16: TMA FEE | B16: 2000 | C16: 0 | D16: 2000
A17: TMP BENIN | B17: 2577210 | C17: 365977 | D17: 2943187
A18: TMP OGBOMOSO | B18: 4859000 | C18: 517000 | D18: 5376000
A19: TMP PORT HARCOURT | B19: 1401076 | C19: 339603 | D19: 1740679
A20: TMP SAPELE | C20: 0 | D20: 1777736
A21: TMP UGHELI | B21: 8122874 | C21: 755500 | D21: 8878374
A22: TMP LAGOS | B22: 0 | C22: 300000 | D22: 300000
A23: Total Revenues | B23: =SUM(B6:B22) -> 2.1542121e+09 | C23: =SUM(C6:C22) -> 1.0341315e+08 | D23: =SUM(D6:D22) -> 2.259403e+09
A25: Other Income (B)
A26: Interest Received from FX | B26: 0 | C26: 0 | D26: =B26+C26 -> 0
A27: TMP Ebrumede | B27: 155200 | C27: 100700 | D27: =B27+C27 -> 255900
A28: TMP Orhuwhorun | B28: 430000 | C28: 170192 | D28: =B28+C28 -> 600192
A29: TMP Osubi | B29: 883000 | C29: 129000 | D29: =B29+C29 -> 1012000
A30: TMP Otokutu | B30: 647617 | C30: 0 | D30: =B30+C30 -> 647617
A31: TMP Ubeji | B31: 94047 | C31: 0 | D31: =B31+C31 -> 94047
A32: TMP Udu | B32: 475300 | C32: 113000 | D32: =B32+C32 -> 588300
A33: TMP Ugbuwangue | B33: 464878 | C33: 0 | D33: =B33+C33 -> 464878
A34: TMP Ughoton | B34: 559880 | C34: 49100 | D34: =B34+C34 -> 608980
A35: TMP Warri Central | B35: 2325000 | C35: 190000 | D35: =B35+C35 -> 2515000
A36: TMP Warri G.R.A | B36: 42000 | C36: 21600 | D36: =B36+C36 -> 63600
A37: Total for other Income | B37: =SUM(B26:B36) -> 6076922 | C37: =SUM(C26:C36) -> 773592 | D37: =SUM(D26:D36) -> 6850514
A39: TOTAL REVENUE | B39: =B23+B37 -> 2.160289e+09 | C39: =C23+C37 -> 1.0418674e+08 | D39: =D23+D37 -> 2.2662535e+09
A42: Expenditure (C)
A43: Advert & Publicity | B43: 86913732 | C43: 8974672 | D43: =B43+C43 -> 95888404
A44: Allowances and Bonus | B44: 6990000 | C44: 0 | D44: =B44+C44 -> 6990000
A45: Bank Charges | B45: 4782718 | C45: 278835 | D45: =B45+C45 -> 5061553
A46: Chairs/Canopies Rent | B46: 27813000 | C46: 0 | D46: =B46+C46 -> 27813000
A47: Church Service Expense | B47: 4221000 | C47: 530000 | D47: =B47+C47 -> 4751000
A48: Consumables | B48: 3974620 | C48: 845410 | D48: =B48+C48 -> 4820030
A49: Diesel | B49: 77406000 | C49: 6722500 | D49: =B49+C49 -> 84128500
A50: Electricity | B50: 988000 | C50: 200000 | D50: =B50+C50 -> 1188000
A51: Entertainment | B51: 13638900 | C51: 1103900 | D51: =B51+C51 -> 14742800
A52: Forex Expense | B52: 3788000 | C52: 0 | D52: =B52+C52 -> 3788000
A53: Fuel | B53: 26077000 | C53: 2045000 | D53: =B53+C53 -> 28122000
A54: Generator Repairs & Mtce | B54: 3355200 | C54: 124000 | D54: =B54+C54 -> 3479200
... A79: Kingdom Investment | B79: 198705000 | C79: 21000000 | D79: =B79+C79 -> 219705000
A80: Total Expenses | B80: =SUM(B43:B79) -> 1304921777 | C80: =ROUND(SUBTOTAL(9, C42:C79), 5) -> 91626007 | D80: =B80+C80 -> 1396547784
A82: Net Income | B82: =B39-B80 -> 8.5536724e+08 | C82: =C39-C80 -> 12560738 | D82: =D39-D80 -> 8.6970571e+08
A84: Cash Flow (C)
A85: Building | B85: -792506000 | C85: -7062500 | D85: =B85+C85 -> -799568500
A86: Equipment | B86: -6196600 | D86: =B86+C86 -> -6196600
A87: Furniture and Fittings | B87: -6104600 | D87: =B87+C87 -> -6104600
A88: Land | B88: 0 | D88: =B88+C88 -> 0
A89: Motor Vehicles | D89: =B89+C89 -> 0
A90: ZENITH REMMITANCE | B90: 4240.2 | D90: =B90+C90 -> 4240.2
A91: UBA | C91: 37750.52 | D91: =B91+C91 -> 37750.52
A92: GTB DOMICILIARY | B92: 21469.6 | C92: 22452.63 | D92: =B92+C92 -> 43922.23
A93: Net cash used in Investing | B93: -8.0478062e+08 | C93: =C86+C87+C92+C85+C91+C90 -> -7002296.9 | D93: =SUM(D85:D92) -> -8.1178379e+08
A96: Net Surplus or Deficit | B96: =VLOOKUP(A96,'October Financial Statement'!A96:D180,4,0) -> 1.3373326e+08 | C96: =C82+C93 -> 5558441.1 | D96: =D82+D93 -> 57921927

Sheet December Financial Statement
A1: The Master's Place International Church, Headquaters -Warri
A2: Income & Expenditure Statement
A3: 46022
A5: DESCRIPTION | B5: Balance B/F | C5: December | D5: YEAR TO DATE
A6: Opening Balance | B6: 85321128 | C6: 5498237.1 | D6: =B6+C6 -> 90819365
A7: Income (A)
A8: Home Connect Offering | B8: 2444370 | C8: 331570 | D8: =B8+C8 -> 2775940
A9: OFFERING | B9: 201883019 | C9: 16478189 | D9: =B9+C9 -> 218361208
A10: PROJECT OFFERING | B10: 1038105910 | C10: 59953718 | D10: =B10+C10 -> 1098059628
A11: SACRIFICE | B11: 667748989 | C11: 10710000 | D11: =B11+C11 -> 678458989
A12: STUDIO-RESOURCE MATERIAL | B12: 16218379 | C12: 380803 | D12: =B12+C12 -> 16599182
A13: SALES OF MATERIAL OFFERING | B13: 0 | C13: 0 | D13: =B13+C13 -> 0
A14: THANKSGIVING OFFERING | B14: 39119056 | C14: 14756976 | D14: =B14+C14 -> 53876032
A15: TITHE | B15: 187534709 | C15: 31400509 | D15: =B15+C15 -> 218935218
A16: TMA FEE | B16: 2000 | C16: 0 | D16: =B16+C16 -> 2000
A17: TMP BENIN | B17: 2943187 | C17: 477826 | D17: =B17+C17 -> 3421013
A18: TMP OGBOMOSO | B18: 5376000 | C18: 1320000 | D18: =B18+C18 -> 6696000
A19: TMP PORTHARCOURT | B19: 1740679 | C19: 0 | D19: =B19+C19 -> 1740679
... A22: TMP LAGOS | B22: 300000 | C22: 1057000 | D22: =B22+C22 -> 1357000
A23: Total Revenues | B23: =SUM(B6:B22) -> 2.2593935e+09 | C23: =SUM(C6:C22) -> 1.438355e+08 | D23: =B23+C23 -> 2.403229e+09
A25: Other Income (B)
A26: Interest Received from FX | B26: 0 | C26: 0 | D26: =B26+C26 -> 0
A27: TMP Ebrumede | B27: 255900 | C27: 80700 | D27: =B27+C27 -> 336600
A28: TMP Orhuwhorun | B28: 600192 | C28: 200000 | D28: =B28+C28 -> 800192
A29: TMP Osubi | B29: 1012000 | C29: 118000 | D29: =B29+C29 -> 1130000
A30: TMP Otokutu | B30: 647617 | C30: 78668 | D30: =B30+C30 -> 726285
A31: TMP Ubeji | B31: 94047 | C31: 0 | D31: =B31+C31 -> 94047
A32: TMP Udu | B32: 588300 | C32: 206000 | D32: =B32+C32 -> 794300
A33: TMP Ugbuwangue | B33: 464878 | C33: 0 | D33: =B33+C33 -> 464878
A34: TMP Ughoton | B34: 608980 | C34: 85740 | D34: =B34+C34 -> 694720
A35: TMP Warri Central | B35: 2515000 | C35: 110000 | D35: =B35+C35 -> 2625000
A36: TMP Warri G.R.A | B36: 63600 | C36: 46100 | D36: =B36+C36 -> 109700
A37: Total for other Income | B37: =SUM(B26:B36) -> 6850514 | C37: =SUM(C26:C36) -> 925208 | D37: =SUM(D26:D36) -> 7775722
A39: TOTAL REVENUE | B39: =B23+B37 -> 2.2662441e+09 | C39: =C23+C37 -> 1.4476071e+08 | D39: =D23+D37 -> 2.4110048e+09
A42: Expenditure (C)
A43: Advert & Publicity | B43: 95888404 | C43: 4193000 | D43: =B43+C43 -> 100081404
A44: Allowances and Bonus | B44: 6990000 | C44: 0 | D44: =B44+C44 -> 6990000
A45: Bank Charges | B45: 5061553 | C45: 394433 | D45: =B45+C45 -> 5455986
A46: Chairs/Canopies Rent | B46: 27813000 | C46: 0 | D46: =B46+C46 -> 27813000
A47: Church Service Expense | B47: 4751000 | C47: 441000 | D47: =B47+C47 -> 5192000
A48: Consumables | B48: 4820030 | C48: 348340 | D48: =B48+C48 -> 5168370
A49: Diesel | B49: 84128500 | C49: 8720000 | D49: =B49+C49 -> 92848500
A50: Electricity | B50: 1188000 | C50: 150000 | D50: =B50+C50 -> 1338000
A51: Entertainment | B51: 14742800 | C51: 180000 | D51: =B51+C51 -> 14922800
A52: Forex Expense | B52: 3788000 | C52: 0 | D52: =B52+C52 -> 3788000
A53: Fuel | B53: 28122000 | C53: 2226000 | D53: =B53+C53 -> 30348000
A54: Generator Repairs & Mtce | B54: 3479200 | C54: 0 | D54: =B54+C54 -> 3479200
... A79: Kingdom Investment | B79: 219705000 | C79: 0 | D79: =B79+C79 -> 219705000
A80: Total Expenses | B80: =SUM(B43:B79) -> 1396547784 | C80: =ROUND(SUBTOTAL(9, C42:C79), 5) -> 126453503 | D80: =B80+C80 -> 1523001287
A82: Net Income | B82: =B39-B80 -> 8.6969627e+08 | C82: =C39-C80 -> 18307205 | D82: =SUM(B82:C82) -> 8.8800347e+08
A84: Cash Flow (C)
A85: Building | B85: -799568500 | C85: -11062500 | D85: =B85+C85 -> -810631000
A86: Equipment | B86: -6196600 | D86: =B86+C86 -> -6196600
A87: Furniture and Fittings | B87: -6104600 | D87: =B87+C87 -> -6104600
A88: Land | B88: 0 | D88: =B88+C88 -> 0
A89: Motor Vehicles | B89: 0 | D89: =B89+C89 -> 0
A90: Current Liabilities | B90: 0 | D90: =B90+C90 -> 0
A91: UBA | B91: 37750.52 | D91: 37750.52
A92: GTB Domiciliary | B92: 43922.23 | D92: 43922.23
A93: Zenith Bank Remittance | B93: 4240.2 | D93: 4240.2
A95: Net cash used in Investing | B95: =B86+B87+B89+B85+B93+B91+B92 -> -8.1178379e+08 | C95: =C86+C87+C89+C85+C90 -> -11062500 | D95: =SUM(D85:D93) -> -8.2284629e+08
A98: Net Surplus or Deficit | B98: =B82+B95 -> 57912479 | C98: =C82+C95 -> 7244705.1 | D98: =D82+D95 -> 65157184

Sheet Expenses
A1: The Master's Place International Church, Headquaters -Warri
A2: Diesel and Rental Expenses for the Year 2025
A4: Item | B4: Amount
A5: Diesel | B5: 103782200
A6: LED Hire | B6: 18640000
A7: Maque Tent ( Car Wash) | B7: 15600000
A8: Bagoda Tent (Church Compound) | B8: 27200000
A9: Chairs | B9: 6292000
A10: TOTAL | B10: =SUM(B5:B9) -> 171514200
